07/timer.v
`include "define.h"
module timer (input [`MEM_ADDR_WIDTH-1:0] addr, input [`DATA_WIDTH-1:0] idata, output [`DATA_WIDTH-1:0] odata, input cs_, input rw_, input clk);
	reg [31:0] count;
	reg en;
	wire clear, start, stop;
	assign clear = (cs_ == `Enable_ && rw_ == `Write && addr == 4 && idata == 1);
        assign start = (cs_ == `Enable_ && rw_ == `Write && addr == 4 && idata == 2);
        assign stop = (cs_ == `Enable_ && rw_ == `Write && addr == 4 && idata == 4);

	always @ (posedge clk)
		if (clear)	count <= 0;
		else if (en)	count <= count + 1;
	always @ (posedge clk)
		if (start)	en <= `Enable;
		else if (stop)	en <= `Disenable;
	assign odata = (addr == 0) ? count[7:0] :
		       (addr == 1) ? count[15:8] :
		       (addr == 2) ? count[23:16] :
		       (addr == 3) ? count[31:24] : 0;
endmodule

07/sram.v
`include "define.h"
module sram (input [`MEM_ADDR_WIDTH-1:0] addr, input [`DATA_WIDTH-1:0] idata, output [`DATA_WIDTH-1:0] odata, input cs_, input rw_, input clk);
	reg[`DATA_WIDTH-1:0] mem [(1<<`MEM_ADDR_WIDTH)-1:0];
	assign odata = mem[addr];
	always @ (posedge clk)
		if (cs_ == `Enable_ && rw_ ==`Write)
			mem[addr] = idata;
endmodule

07/addrdec.v
`include "define.h"
module addrdec (input [`BUS_ADDR_WIDTH-1:0] addr, output cs0_, output cs1_, output cs2_, output cs3_);
	assign cs0_ = addr[8] || addr[9];
	assign cs1_ = ~addr[8] || addr[9];
	assign cs2_ = addr[8] || ~addr[9];
	assign cs3_ = ~(addr[8] && addr[9]);
endmodule

07/top.v
`include "define.h"
module top (input [`BUS_ADDR_WIDTH-1:0] addr, input [`DATA_WIDTH-1:0] idata, output [`DATA_WIDTH-1:0] odata, input rw_, input reset_, input clk);
	wire [`DATA_WIDTH-1:0] odata0, odata1, odata2;
	wire cs0_, cs1_, cs2_, cs3_;
	addrdec u0 (addr, cs0_, cs1_, cs2_, cs3_);
	sram	u1 (addr[`MEM_ADDR_WIDTH-1:0], idata, odata0, cs0_, rw_, clk);
	sram	u2 (addr[`MEM_ADDR_WIDTH-1:0], idata, odata1, cs1_, rw_, clk);
	timer 	u3 (addr[`MEM_ADDR_WIDTH-1:0], idata, odata2, cs2_, rw_, clk);
	assign odata = (cs0_ == `Enable_) ? odata0 :
		       (cs1_ == `Enable_) ? odata1 : 
		       (cs2_ == `Enable_) ? odata2 : 0;
endmodule

07/test.v
`timescale 1ns/10ps
`include "define.h"
module test();
	reg [`BUS_ADDR_WIDTH-1:0] addr;
	reg [`DATA_WIDTH-1:0] idata;
        wire [`DATA_WIDTH-1:0] odata;
	reg rw_, reset_, clk;
	top u0 (addr, idata, odata, rw_, reset_, clk);
	always begin
		clk <= 1; #1; clk <= 0; #1;
	end
	initial begin
		#1;
		$dumpfile("dump.vcd");
		$dumpvars(0, test.u0);
		$display("timer <clear>");
                rw_ <= `Write;
                addr <= 10'h204;
                idata <= 1;
                #2;
                $display("timer <start>");
                rw_ <= `Write;
                addr <= 10'h204;
                idata <= 2;
                #2;
		rw_ <= `Write;
		addr <= 10'h120; 
		idata <= 8'h99; 
		#2;
		rw_ <= `Read;
                addr <= 10'h120; 
                idata <= 0; 
		#2;
		$display("mem1");
		$display("addr=%h odata=%h cs0_=%b cs1_=%b cs2_=%b", addr, odata, u0.u0.cs0_, u0.u0.cs1_, u0.u0.cs2_);
	        rw_ <= `Write;
                addr <= 10'h20; 
                idata <= 8'h99; 
                #2;
                rw_ <= `Read;
                addr <= 10'h20; 
                idata <= 0; 
                #2;
		$display("mem2");
                $display("addr=%h odata=%h cs0_=%b cs1_=%b cs2_=%b", addr, odata, u0.u0.cs0_, u0.u0.cs1_, u0.u0.cs2_);
		$display("timer <stop>");
		rw_ <= `Write;
		addr <= 10'h204;
		idata <= 4;
		#2;
		rw_ <= `Read;
		addr <= 10'h200;
		#2;
		$display("addr=%h odata=%h cs0_=%b cs1_=%b cs2_=%b", addr, odata, u0.u0.cs0_, u0.u0.cs1_, u0.u0.cs2_);
                rw_ <= `Read;
                addr <= 10'h201;
                #2;
                $display("addr=%h odata=%h cs0_=%b cs1_=%b cs2_=%b", addr, odata, u0.u0.cs0_, u0.u0.cs1_, u0.u0.cs2_);
                rw_ <= `Read;
                addr <= 10'h202;
                #2;
                $display("addr=%h odata=%h cs0_=%b cs1_=%b cs2_=%b", addr, odata, u0.u0.cs0_, u0.u0.cs1_, u0.u0.cs2_);
                rw_ <= `Read;
                addr <= 10'h203;
                #2;
                $display("addr=%h odata=%h cs0_=%b cs1_=%b cs2_=%b", addr, odata, u0.u0.cs0_, u0.u0.cs1_, u0.u0.cs2_);
				
		$display("timer <clear>");
                rw_ <= `Write;
                addr <= 10'h204;
                idata <= 1;
                #2;
                rw_ <= `Read;
                addr <= 10'h200;
                #2;
                $display("addr=%h odata=%h cs0_=%b cs1_=%b cs2_=%b", addr, odata, u0.u0.cs0_, u0.u0.cs1_, u0.u0.cs2_);
                rw_ <= `Read;
                addr <= 10'h201;
                #2;
                $display("addr=%h odata=%h cs0_=%b cs1_=%b cs2_=%b", addr, odata, u0.u0.cs0_, u0.u0.cs1_, u0.u0.cs2_);
                rw_ <= `Read;
                addr <= 10'h202;
                #2;
                $display("addr=%h odata=%h cs0_=%b cs1_=%b cs2_=%b", addr, odata, u0.u0.cs0_, u0.u0.cs1_, u0.u0.cs2_);
                rw_ <= `Read;
                addr <= 10'h203;
                #2;
                $display("addr=%h odata=%h cs0_=%b cs1_=%b cs2_=%b", addr, odata, u0.u0.cs0_, u0.u0.cs1_, u0.u0.cs2_);

		$display("timer <start>");
                rw_ <= `Write;
                addr <= 10'h204;
                idata <= 2;
                #1000
		$display("#1000");
		$display("timer <stop>");
                rw_ <= `Write;
                addr <= 10'h204;
                idata <= 4;
                rw_ <= `Read;
                addr <= 10'h200;
                #2;
                $display("addr=%h odata=%h cs0_=%b cs1_=%b cs2_=%b", addr, odata, u0.u0.cs0_, u0.u0.cs1_, u0.u0.cs2_);
                rw_ <= `Read;
                addr <= 10'h201;
                #2;
                $display("addr=%h odata=%h cs0_=%b cs1_=%b cs2_=%b", addr, odata, u0.u0.cs0_, u0.u0.cs1_, u0.u0.cs2_);
                rw_ <= `Read;
                addr <= 10'h202;
                #2;
                $display("addr=%h odata=%h cs0_=%b cs1_=%b cs2_=%b", addr, odata, u0.u0.cs0_, u0.u0.cs1_, u0.u0.cs2_);
                rw_ <= `Read;
                addr <= 10'h203;
                #2;
                $display("addr=%h odata=%h cs0_=%b cs1_=%b cs2_=%b", addr, odata, u0.u0.cs0_, u0.u0.cs1_, u0.u0.cs2_);
		$finish;
	end
endmodule

07/dump.vcd
$date
    May 25, 2018  12:49:22
$end
$version
    TOOL:	ncsim	06.20-s004
$end
$timescale
    10 ps
$end

$scope module test $end

$scope module u0 $end
$var wire     10 !    addr [9:0] $end
$var wire      8 "    idata [7:0] $end
$var wire      8 #    odata [7:0] $end
$var wire      1 $    rw_  $end
$var wire      1 %    reset_  $end
$var wire      1 &    clk  $end
$var wire      8 '    odata0 [7:0] $end
$var wire      8 (    odata1 [7:0] $end
$var wire      8 )    odata2 [7:0] $end
$var wire      1 *    cs0_  $end
$var wire      1 +    cs1_  $end
$var wire      1 ,    cs2_  $end
$var wire      1 -    cs3_  $end

$scope module u0 $end
$var wire     10 !    addr [9:0] $end
$var wire      1 *    cs0_  $end
$var wire      1 +    cs1_  $end
$var wire      1 ,    cs2_  $end
$var wire      1 -    cs3_  $end
$upscope $end


$scope module u1 $end
$var wire      8 .    addr [7:0] $end
$var wire      8 "    idata [7:0] $end
$var wire      8 '    odata [7:0] $end
$var wire      1 *    cs_  $end
$var wire      1 $    rw_  $end
$var wire      1 &    clk  $end
$upscope $end


$scope module u2 $end
$var wire      8 .    addr [7:0] $end
$var wire      8 "    idata [7:0] $end
$var wire      8 (    odata [7:0] $end
$var wire      1 +    cs_  $end
$var wire      1 $    rw_  $end
$var wire      1 &    clk  $end
$upscope $end


$scope module u3 $end
$var wire      8 .    addr [7:0] $end
$var wire      8 "    idata [7:0] $end
$var wire      8 )    odata [7:0] $end
$var wire      1 ,    cs_  $end
$var wire      1 $    rw_  $end
$var wire      1 &    clk  $end
$var reg      32 /    count [31:0] $end
$var reg       1 0    en  $end
$var wire      1 1    clear  $end
$var wire      1 2    start  $end
$var wire      1 3    stop  $end
$upscope $end

$upscope $end

$upscope $end

$enddefinitions $end
#100
$dumpvars
b1000000100 !
b1 "
b0 #
0$
x%
0&
bx '
bx (
b0 )
1*
1+
0,
1-
b100 .
bx /
x0
11
02
03
$end
#200
1&
b0 /
#300
0&
b10 "
12
01
#400
1&
10
#500
b100100000 !
0&
b10011001 "
02
b100000 .
1,
0+
bx #
#600
1&
b10011001 (
b10011001 #
b1 /
#700
0&
b0 "
1$
#800
1&
b10 /
#900
b100000 !
0&
b10011001 "
0$
1+
0*
bx #
#1000
1&
b10011001 '
b10011001 #
b11 /
#1100
0&
b0 "
1$
#1200
1&
b100 /
#1300
b1000000100 !
0&
b100 "
0$
b100 .
0,
1*
b0 #
bx '
bx (
13
#1400
1&
00
b101 /
#1500
b1000000000 !
0&
1$
03
b0 .
b101 )
b101 #
#1600
1&
#1700
b1000000001 !
0&
b1 .
b0 )
b0 #
#1800
1&
#1900
b1000000010 !
0&
b10 .
#2000
1&
#2100
b1000000011 !
0&
b11 .
#2200
1&
#2300
b1000000100 !
0&
b1 "
0$
b100 .
11
#2400
1&
b0 /
#2500
b1000000000 !
0&
1$
01
b0 .
#2600
1&
#2700
b1000000001 !
0&
b1 .
#2800
1&
#2900
b1000000010 !
0&
b10 .
#3000
1&
#3100
b1000000011 !
0&
b11 .
#3200
1&
#3300
b1000000100 !
0&
b10 "
0$
b100 .
12
#3400
1&
10
#3500
0&
#3600
1&
b1 /
#3700
0&
#3800
1&
b10 /
#3900
0&
#4000
1&
b11 /
#4100
0&
#4200
1&
b100 /
#4300
0&
#4400
1&
b101 /
#4500
0&
#4600
1&
b110 /
#4700
0&
#4800
1&
b111 /
#4900
0&
#5000
1&
b1000 /
#5100
0&
#5200
1&
b1001 /
#5300
0&
#5400
1&
b1010 /
#5500
0&
#5600
1&
b1011 /
#5700
0&
#5800
1&
b1100 /
#5900
0&
#6000
1&
b1101 /
#6100
0&
#6200
1&
b1110 /
#6300
0&
#6400
1&
b1111 /
#6500
0&
#6600
1&
b10000 /
#6700
0&
#6800
1&
b10001 /
#6900
0&
#7000
1&
b10010 /
#7100
0&
#7200
1&
b10011 /
#7300
0&
#7400
1&
b10100 /
#7500
0&
#7600
1&
b10101 /
#7700
0&
#7800
1&
b10110 /
#7900
0&
#8000
1&
b10111 /
#8100
0&
#8200
1&
b11000 /
#8300
0&
#8400
1&
b11001 /
#8500
0&
#8600
1&
b11010 /
#8700
0&
#8800
1&
b11011 /
#8900
0&
#9000
1&
b11100 /
#9100
0&
#9200
1&
b11101 /
#9300
0&
#9400
1&
b11110 /
#9500
0&
#9600
1&
b11111 /
#9700
0&
#9800
1&
b100000 /
#9900
0&
#10000
1&
b100001 /
#10100
0&
#10200
1&
b100010 /
#10300
0&
#10400
1&
b100011 /
#10500
0&
#10600
1&
b100100 /
#10700
0&
#10800
1&
b100101 /
#10900
0&
#11000
1&
b100110 /
#11100
0&
#11200
1&
b100111 /
#11300
0&
#11400
1&
b101000 /
#11500
0&
#11600
1&
b101001 /
#11700
0&
#11800
1&
b101010 /
#11900
0&
#12000
1&
b101011 /
#12100
0&
#12200
1&
b101100 /
#12300
0&
#12400
1&
b101101 /
#12500
0&
#12600
1&
b101110 /
#12700
0&
#12800
1&
b101111 /
#12900
0&
#13000
1&
b110000 /
#13100
0&
#13200
1&
b110001 /
#13300
0&
#13400
1&
b110010 /
#13500
0&
#13600
1&
b110011 /
#13700
0&
#13800
1&
b110100 /
#13900
0&
#14000
1&
b110101 /
#14100
0&
#14200
1&
b110110 /
#14300
0&
#14400
1&
b110111 /
#14500
0&
#14600
1&
b111000 /
#14700
0&
#14800
1&
b111001 /
#14900
0&
#15000
1&
b111010 /
#15100
0&
#15200
1&
b111011 /
#15300
0&
#15400
1&
b111100 /
#15500
0&
#15600
1&
b111101 /
#15700
0&
#15800
1&
b111110 /
#15900
0&
#16000
1&
b111111 /
#16100
0&
#16200
1&
b1000000 /
#16300
0&
#16400
1&
b1000001 /
#16500
0&
#16600
1&
b1000010 /
#16700
0&
#16800
1&
b1000011 /
#16900
0&
#17000
1&
b1000100 /
#17100
0&
#17200
1&
b1000101 /
#17300
0&
#17400
1&
b1000110 /
#17500
0&
#17600
1&
b1000111 /
#17700
0&
#17800
1&
b1001000 /
#17900
0&
#18000
1&
b1001001 /
#18100
0&
#18200
1&
b1001010 /
#18300
0&
#18400
1&
b1001011 /
#18500
0&
#18600
1&
b1001100 /
#18700
0&
#18800
1&
b1001101 /
#18900
0&
#19000
1&
b1001110 /
#19100
0&
#19200
1&
b1001111 /
#19300
0&
#19400
1&
b1010000 /
#19500
0&
#19600
1&
b1010001 /
#19700
0&
#19800
1&
b1010010 /
#19900
0&
#20000
1&
b1010011 /
#20100
0&
#20200
1&
b1010100 /
#20300
0&
#20400
1&
b1010101 /
#20500
0&
#20600
1&
b1010110 /
#20700
0&
#20800
1&
b1010111 /
#20900
0&
#21000
1&
b1011000 /
#21100
0&
#21200
1&
b1011001 /
#21300
0&
#21400
1&
b1011010 /
#21500
0&
#21600
1&
b1011011 /
#21700
0&
#21800
1&
b1011100 /
#21900
0&
#22000
1&
b1011101 /
#22100
0&
#22200
1&
b1011110 /
#22300
0&
#22400
1&
b1011111 /
#22500
0&
#22600
1&
b1100000 /
#22700
0&
#22800
1&
b1100001 /
#22900
0&
#23000
1&
b1100010 /
#23100
0&
#23200
1&
b1100011 /
#23300
0&
#23400
1&
b1100100 /
#23500
0&
#23600
1&
b1100101 /
#23700
0&
#23800
1&
b1100110 /
#23900
0&
#24000
1&
b1100111 /
#24100
0&
#24200
1&
b1101000 /
#24300
0&
#24400
1&
b1101001 /
#24500
0&
#24600
1&
b1101010 /
#24700
0&
#24800
1&
b1101011 /
#24900
0&
#25000
1&
b1101100 /
#25100
0&
#25200
1&
b1101101 /
#25300
0&
#25400
1&
b1101110 /
#25500
0&
#25600
1&
b1101111 /
#25700
0&
#25800
1&
b1110000 /
#25900
0&
#26000
1&
b1110001 /
#26100
0&
#26200
1&
b1110010 /
#26300
0&
#26400
1&
b1110011 /
#26500
0&
#26600
1&
b1110100 /
#26700
0&
#26800
1&
b1110101 /
#26900
0&
#27000
1&
b1110110 /
#27100
0&
#27200
1&
b1110111 /
#27300
0&
#27400
1&
b1111000 /
#27500
0&
#27600
1&
b1111001 /
#27700
0&
#27800
1&
b1111010 /
#27900
0&
#28000
1&
b1111011 /
#28100
0&
#28200
1&
b1111100 /
#28300
0&
#28400
1&
b1111101 /
#28500
0&
#28600
1&
b1111110 /
#28700
0&
#28800
1&
b1111111 /
#28900
0&
#29000
1&
b10000000 /
#29100
0&
#29200
1&
b10000001 /
#29300
0&
#29400
1&
b10000010 /
#29500
0&
#29600
1&
b10000011 /
#29700
0&
#29800
1&
b10000100 /
#29900
0&
#30000
1&
b10000101 /
#30100
0&
#30200
1&
b10000110 /
#30300
0&
#30400
1&
b10000111 /
#30500
0&
#30600
1&
b10001000 /
#30700
0&
#30800
1&
b10001001 /
#30900
0&
#31000
1&
b10001010 /
#31100
0&
#31200
1&
b10001011 /
#31300
0&
#31400
1&
b10001100 /
#31500
0&
#31600
1&
b10001101 /
#31700
0&
#31800
1&
b10001110 /
#31900
0&
#32000
1&
b10001111 /
#32100
0&
#32200
1&
b10010000 /
#32300
0&
#32400
1&
b10010001 /
#32500
0&
#32600
1&
b10010010 /
#32700
0&
#32800
1&
b10010011 /
#32900
0&
#33000
1&
b10010100 /
#33100
0&
#33200
1&
b10010101 /
#33300
0&
#33400
1&
b10010110 /
#33500
0&
#33600
1&
b10010111 /
#33700
0&
#33800
1&
b10011000 /
#33900
0&
#34000
1&
b10011001 /
#34100
0&
#34200
1&
b10011010 /
#34300
0&
#34400
1&
b10011011 /
#34500
0&
#34600
1&
b10011100 /
#34700
0&
#34800
1&
b10011101 /
#34900
0&
#35000
1&
b10011110 /
#35100
0&
#35200
1&
b10011111 /
#35300
0&
#35400
1&
b10100000 /
#35500
0&
#35600
1&
b10100001 /
#35700
0&
#35800
1&
b10100010 /
#35900
0&
#36000
1&
b10100011 /
#36100
0&
#36200
1&
b10100100 /
#36300
0&
#36400
1&
b10100101 /
#36500
0&
#36600
1&
b10100110 /
#36700
0&
#36800
1&
b10100111 /
#36900
0&
#37000
1&
b10101000 /
#37100
0&
#37200
1&
b10101001 /
#37300
0&
#37400
1&
b10101010 /
#37500
0&
#37600
1&
b10101011 /
#37700
0&
#37800
1&
b10101100 /
#37900
0&
#38000
1&
b10101101 /
#38100
0&
#38200
1&
b10101110 /
#38300
0&
#38400
1&
b10101111 /
#38500
0&
#38600
1&
b10110000 /
#38700
0&
#38800
1&
b10110001 /
#38900
0&
#39000
1&
b10110010 /
#39100
0&
#39200
1&
b10110011 /
#39300
0&
#39400
1&
b10110100 /
#39500
0&
#39600
1&
b10110101 /
#39700
0&
#39800
1&
b10110110 /
#39900
0&
#40000
1&
b10110111 /
#40100
0&
#40200
1&
b10111000 /
#40300
0&
#40400
1&
b10111001 /
#40500
0&
#40600
1&
b10111010 /
#40700
0&
#40800
1&
b10111011 /
#40900
0&
#41000
1&
b10111100 /
#41100
0&
#41200
1&
b10111101 /
#41300
0&
#41400
1&
b10111110 /
#41500
0&
#41600
1&
b10111111 /
#41700
0&
#41800
1&
b11000000 /
#41900
0&
#42000
1&
b11000001 /
#42100
0&
#42200
1&
b11000010 /
#42300
0&
#42400
1&
b11000011 /
#42500
0&
#42600
1&
b11000100 /
#42700
0&
#42800
1&
b11000101 /
#42900
0&
#43000
1&
b11000110 /
#43100
0&
#43200
1&
b11000111 /
#43300
0&
#43400
1&
b11001000 /
#43500
0&
#43600
1&
b11001001 /
#43700
0&
#43800
1&
b11001010 /
#43900
0&
#44000
1&
b11001011 /
#44100
0&
#44200
1&
b11001100 /
#44300
0&
#44400
1&
b11001101 /
#44500
0&
#44600
1&
b11001110 /
#44700
0&
#44800
1&
b11001111 /
#44900
0&
#45000
1&
b11010000 /
#45100
0&
#45200
1&
b11010001 /
#45300
0&
#45400
1&
b11010010 /
#45500
0&
#45600
1&
b11010011 /
#45700
0&
#45800
1&
b11010100 /
#45900
0&
#46000
1&
b11010101 /
#46100
0&
#46200
1&
b11010110 /
#46300
0&
#46400
1&
b11010111 /
#46500
0&
#46600
1&
b11011000 /
#46700
0&
#46800
1&
b11011001 /
#46900
0&
#47000
1&
b11011010 /
#47100
0&
#47200
1&
b11011011 /
#47300
0&
#47400
1&
b11011100 /
#47500
0&
#47600
1&
b11011101 /
#47700
0&
#47800
1&
b11011110 /
#47900
0&
#48000
1&
b11011111 /
#48100
0&
#48200
1&
b11100000 /
#48300
0&
#48400
1&
b11100001 /
#48500
0&
#48600
1&
b11100010 /
#48700
0&
#48800
1&
b11100011 /
#48900
0&
#49000
1&
b11100100 /
#49100
0&
#49200
1&
b11100101 /
#49300
0&
#49400
1&
b11100110 /
#49500
0&
#49600
1&
b11100111 /
#49700
0&
#49800
1&
b11101000 /
#49900
0&
#50000
1&
b11101001 /
#50100
0&
#50200
1&
b11101010 /
#50300
0&
#50400
1&
b11101011 /
#50500
0&
#50600
1&
b11101100 /
#50700
0&
#50800
1&
b11101101 /
#50900
0&
#51000
1&
b11101110 /
#51100
0&
#51200
1&
b11101111 /
#51300
0&
#51400
1&
b11110000 /
#51500
0&
#51600
1&
b11110001 /
#51700
0&
#51800
1&
b11110010 /
#51900
0&
#52000
1&
b11110011 /
#52100
0&
#52200
1&
b11110100 /
#52300
0&
#52400
1&
b11110101 /
#52500
0&
#52600
1&
b11110110 /
#52700
0&
#52800
1&
b11110111 /
#52900
0&
#53000
1&
b11111000 /
#53100
0&
#53200
1&
b11111001 /
#53300
0&
#53400
1&
b11111010 /
#53500
0&
#53600
1&
b11111011 /
#53700
0&
#53800
1&
b11111100 /
#53900
0&
#54000
1&
b11111101 /
#54100
0&
#54200
1&
b11111110 /
#54300
0&
#54400
1&
b11111111 /
#54500
0&
#54600
1&
b100000000 /
#54700
0&
#54800
1&
b100000001 /
#54900
0&
#55000
1&
b100000010 /
#55100
0&
#55200
1&
b100000011 /
#55300
0&
#55400
1&
b100000100 /
#55500
0&
#55600
1&
b100000101 /
#55700
0&
#55800
1&
b100000110 /
#55900
0&
#56000
1&
b100000111 /
#56100
0&
#56200
1&
b100001000 /
#56300
0&
#56400
1&
b100001001 /
#56500
0&
#56600
1&
b100001010 /
#56700
0&
#56800
1&
b100001011 /
#56900
0&
#57000
1&
b100001100 /
#57100
0&
#57200
1&
b100001101 /
#57300
0&
#57400
1&
b100001110 /
#57500
0&
#57600
1&
b100001111 /
#57700
0&
#57800
1&
b100010000 /
#57900
0&
#58000
1&
b100010001 /
#58100
0&
#58200
1&
b100010010 /
#58300
0&
#58400
1&
b100010011 /
#58500
0&
#58600
1&
b100010100 /
#58700
0&
#58800
1&
b100010101 /
#58900
0&
#59000
1&
b100010110 /
#59100
0&
#59200
1&
b100010111 /
#59300
0&
#59400
1&
b100011000 /
#59500
0&
#59600
1&
b100011001 /
#59700
0&
#59800
1&
b100011010 /
#59900
0&
#60000
1&
b100011011 /
#60100
0&
#60200
1&
b100011100 /
#60300
0&
#60400
1&
b100011101 /
#60500
0&
#60600
1&
b100011110 /
#60700
0&
#60800
1&
b100011111 /
#60900
0&
#61000
1&
b100100000 /
#61100
0&
#61200
1&
b100100001 /
#61300
0&
#61400
1&
b100100010 /
#61500
0&
#61600
1&
b100100011 /
#61700
0&
#61800
1&
b100100100 /
#61900
0&
#62000
1&
b100100101 /
#62100
0&
#62200
1&
b100100110 /
#62300
0&
#62400
1&
b100100111 /
#62500
0&
#62600
1&
b100101000 /
#62700
0&
#62800
1&
b100101001 /
#62900
0&
#63000
1&
b100101010 /
#63100
0&
#63200
1&
b100101011 /
#63300
0&
#63400
1&
b100101100 /
#63500
0&
#63600
1&
b100101101 /
#63700
0&
#63800
1&
b100101110 /
#63900
0&
#64000
1&
b100101111 /
#64100
0&
#64200
1&
b100110000 /
#64300
0&
#64400
1&
b100110001 /
#64500
0&
#64600
1&
b100110010 /
#64700
0&
#64800
1&
b100110011 /
#64900
0&
#65000
1&
b100110100 /
#65100
0&
#65200
1&
b100110101 /
#65300
0&
#65400
1&
b100110110 /
#65500
0&
#65600
1&
b100110111 /
#65700
0&
#65800
1&
b100111000 /
#65900
0&
#66000
1&
b100111001 /
#66100
0&
#66200
1&
b100111010 /
#66300
0&
#66400
1&
b100111011 /
#66500
0&
#66600
1&
b100111100 /
#66700
0&
#66800
1&
b100111101 /
#66900
0&
#67000
1&
b100111110 /
#67100
0&
#67200
1&
b100111111 /
#67300
0&
#67400
1&
b101000000 /
#67500
0&
#67600
1&
b101000001 /
#67700
0&
#67800
1&
b101000010 /
#67900
0&
#68000
1&
b101000011 /
#68100
0&
#68200
1&
b101000100 /
#68300
0&
#68400
1&
b101000101 /
#68500
0&
#68600
1&
b101000110 /
#68700
0&
#68800
1&
b101000111 /
#68900
0&
#69000
1&
b101001000 /
#69100
0&
#69200
1&
b101001001 /
#69300
0&
#69400
1&
b101001010 /
#69500
0&
#69600
1&
b101001011 /
#69700
0&
#69800
1&
b101001100 /
#69900
0&
#70000
1&
b101001101 /
#70100
0&
#70200
1&
b101001110 /
#70300
0&
#70400
1&
b101001111 /
#70500
0&
#70600
1&
b101010000 /
#70700
0&
#70800
1&
b101010001 /
#70900
0&
#71000
1&
b101010010 /
#71100
0&
#71200
1&
b101010011 /
#71300
0&
#71400
1&
b101010100 /
#71500
0&
#71600
1&
b101010101 /
#71700
0&
#71800
1&
b101010110 /
#71900
0&
#72000
1&
b101010111 /
#72100
0&
#72200
1&
b101011000 /
#72300
0&
#72400
1&
b101011001 /
#72500
0&
#72600
1&
b101011010 /
#72700
0&
#72800
1&
b101011011 /
#72900
0&
#73000
1&
b101011100 /
#73100
0&
#73200
1&
b101011101 /
#73300
0&
#73400
1&
b101011110 /
#73500
0&
#73600
1&
b101011111 /
#73700
0&
#73800
1&
b101100000 /
#73900
0&
#74000
1&
b101100001 /
#74100
0&
#74200
1&
b101100010 /
#74300
0&
#74400
1&
b101100011 /
#74500
0&
#74600
1&
b101100100 /
#74700
0&
#74800
1&
b101100101 /
#74900
0&
#75000
1&
b101100110 /
#75100
0&
#75200
1&
b101100111 /
#75300
0&
#75400
1&
b101101000 /
#75500
0&
#75600
1&
b101101001 /
#75700
0&
#75800
1&
b101101010 /
#75900
0&
#76000
1&
b101101011 /
#76100
0&
#76200
1&
b101101100 /
#76300
0&
#76400
1&
b101101101 /
#76500
0&
#76600
1&
b101101110 /
#76700
0&
#76800
1&
b101101111 /
#76900
0&
#77000
1&
b101110000 /
#77100
0&
#77200
1&
b101110001 /
#77300
0&
#77400
1&
b101110010 /
#77500
0&
#77600
1&
b101110011 /
#77700
0&
#77800
1&
b101110100 /
#77900
0&
#78000
1&
b101110101 /
#78100
0&
#78200
1&
b101110110 /
#78300
0&
#78400
1&
b101110111 /
#78500
0&
#78600
1&
b101111000 /
#78700
0&
#78800
1&
b101111001 /
#78900
0&
#79000
1&
b101111010 /
#79100
0&
#79200
1&
b101111011 /
#79300
0&
#79400
1&
b101111100 /
#79500
0&
#79600
1&
b101111101 /
#79700
0&
#79800
1&
b101111110 /
#79900
0&
#80000
1&
b101111111 /
#80100
0&
#80200
1&
b110000000 /
#80300
0&
#80400
1&
b110000001 /
#80500
0&
#80600
1&
b110000010 /
#80700
0&
#80800
1&
b110000011 /
#80900
0&
#81000
1&
b110000100 /
#81100
0&
#81200
1&
b110000101 /
#81300
0&
#81400
1&
b110000110 /
#81500
0&
#81600
1&
b110000111 /
#81700
0&
#81800
1&
b110001000 /
#81900
0&
#82000
1&
b110001001 /
#82100
0&
#82200
1&
b110001010 /
#82300
0&
#82400
1&
b110001011 /
#82500
0&
#82600
1&
b110001100 /
#82700
0&
#82800
1&
b110001101 /
#82900
0&
#83000
1&
b110001110 /
#83100
0&
#83200
1&
b110001111 /
#83300
0&
#83400
1&
b110010000 /
#83500
0&
#83600
1&
b110010001 /
#83700
0&
#83800
1&
b110010010 /
#83900
0&
#84000
1&
b110010011 /
#84100
0&
#84200
1&
b110010100 /
#84300
0&
#84400
1&
b110010101 /
#84500
0&
#84600
1&
b110010110 /
#84700
0&
#84800
1&
b110010111 /
#84900
0&
#85000
1&
b110011000 /
#85100
0&
#85200
1&
b110011001 /
#85300
0&
#85400
1&
b110011010 /
#85500
0&
#85600
1&
b110011011 /
#85700
0&
#85800
1&
b110011100 /
#85900
0&
#86000
1&
b110011101 /
#86100
0&
#86200
1&
b110011110 /
#86300
0&
#86400
1&
b110011111 /
#86500
0&
#86600
1&
b110100000 /
#86700
0&
#86800
1&
b110100001 /
#86900
0&
#87000
1&
b110100010 /
#87100
0&
#87200
1&
b110100011 /
#87300
0&
#87400
1&
b110100100 /
#87500
0&
#87600
1&
b110100101 /
#87700
0&
#87800
1&
b110100110 /
#87900
0&
#88000
1&
b110100111 /
#88100
0&
#88200
1&
b110101000 /
#88300
0&
#88400
1&
b110101001 /
#88500
0&
#88600
1&
b110101010 /
#88700
0&
#88800
1&
b110101011 /
#88900
0&
#89000
1&
b110101100 /
#89100
0&
#89200
1&
b110101101 /
#89300
0&
#89400
1&
b110101110 /
#89500
0&
#89600
1&
b110101111 /
#89700
0&
#89800
1&
b110110000 /
#89900
0&
#90000
1&
b110110001 /
#90100
0&
#90200
1&
b110110010 /
#90300
0&
#90400
1&
b110110011 /
#90500
0&
#90600
1&
b110110100 /
#90700
0&
#90800
1&
b110110101 /
#90900
0&
#91000
1&
b110110110 /
#91100
0&
#91200
1&
b110110111 /
#91300
0&
#91400
1&
b110111000 /
#91500
0&
#91600
1&
b110111001 /
#91700
0&
#91800
1&
b110111010 /
#91900
0&
#92000
1&
b110111011 /
#92100
0&
#92200
1&
b110111100 /
#92300
0&
#92400
1&
b110111101 /
#92500
0&
#92600
1&
b110111110 /
#92700
0&
#92800
1&
b110111111 /
#92900
0&
#93000
1&
b111000000 /
#93100
0&
#93200
1&
b111000001 /
#93300
0&
#93400
1&
b111000010 /
#93500
0&
#93600
1&
b111000011 /
#93700
0&
#93800
1&
b111000100 /
#93900
0&
#94000
1&
b111000101 /
#94100
0&
#94200
1&
b111000110 /
#94300
0&
#94400
1&
b111000111 /
#94500
0&
#94600
1&
b111001000 /
#94700
0&
#94800
1&
b111001001 /
#94900
0&
#95000
1&
b111001010 /
#95100
0&
#95200
1&
b111001011 /
#95300
0&
#95400
1&
b111001100 /
#95500
0&
#95600
1&
b111001101 /
#95700
0&
#95800
1&
b111001110 /
#95900
0&
#96000
1&
b111001111 /
#96100
0&
#96200
1&
b111010000 /
#96300
0&
#96400
1&
b111010001 /
#96500
0&
#96600
1&
b111010010 /
#96700
0&
#96800
1&
b111010011 /
#96900
0&
#97000
1&
b111010100 /
#97100
0&
#97200
1&
b111010101 /
#97300
0&
#97400
1&
b111010110 /
#97500
0&
#97600
1&
b111010111 /
#97700
0&
#97800
1&
b111011000 /
#97900
0&
#98000
1&
b111011001 /
#98100
0&
#98200
1&
b111011010 /
#98300
0&
#98400
1&
b111011011 /
#98500
0&
#98600
1&
b111011100 /
#98700
0&
#98800
1&
b111011101 /
#98900
0&
#99000
1&
b111011110 /
#99100
0&
#99200
1&
b111011111 /
#99300
0&
#99400
1&
b111100000 /
#99500
0&
#99600
1&
b111100001 /
#99700
0&
#99800
1&
b111100010 /
