backup/dmactr.v
`timescale 1ns/10ps

`include "define.h"

module dmactr(
	      output reg[`BUS_ADDR_WIDTH-1:0] addr,
	      output reg[`DATA_WIDTH-1:0] odata,
	      input [`DATA_WIDTH-1:0] idata,
	      output reg rw_,
	      output reg breq_,
	      input bgrt_,
	      input [`BUS_ADDR_WIDTH-1:0] dsaddr,
	      input [`BUS_ADDR_WIDTH-1:0] ddaddr,
	      input [1:0] dmode,
	      input dreq_,
	      output reg eop_,
	      input reset_,
	      input clk);

   reg[1:0] 		    state;
   reg [2:0] 		    count;
   reg [`BUS_ADDR_WIDTH-1:0] dsaddreg;
   reg [`BUS_ADDR_WIDTH-1:0] ddaddreg;			     
   always @ (posedge clk)begin
     if(reset_ == `Enable_) begin
	state <= `Wait;
	
     end else begin
	case (dmode)
	  `Single:
       case (state)
	 `Wait: begin if (dreq_ == `Enable_) begin
	    breq_ = `Enable_;
	    state <= `Read1;
	 end
	 eop_ = `Disable_;
	 end
	 `Read1: if (bgrt_ == `Enable_ ) begin
	   addr <= dsaddr;
            rw_ <= `Read;	 
	   state <= `Write1;
	 end
	 `Write1:begin addr <= ddaddr;
	 rw_ <= `Write;
	 odata <= idata;
         state <= `Complete;
	    end
	 `Complete: begin eop_ <= `Enable_;
	 breq_ <= `Disable_;
	 state <= `Wait;
	    end
       endcase // case (state)
	`BURST_MEM_MEM:
	  case (state)
	 `Wait: begin if (dreq_ == `Enable_) begin
	    breq_ <= `Enable_;
	    count <= 4;
	    state <= `Read1;
	 end
	 eop_ <= `Disable_;
	 end
	 `Read1:begin
	   if(count == 4) begin
	      dsaddreg <= dsaddr;
	    ddaddreg <= ddaddr;
	      end
          if (bgrt_ == `Enable_ ) begin
	   addr <= dsaddreg;
            rw_ <= `Read;	 
	   state <= `Write1;
	    count <= count - 1;
	  end
	    end
	 `Write1:begin addr <= ddaddreg;
	 rw_ <= `Write;
	 odata <= idata;
	 if(count != 0) begin
	    dsaddreg <= dsaddreg + 1;
	    ddaddreg <= ddaddreg + 1;
	    state <= `Read1;
	 end else begin
         state <= `Complete;
	 end
	 end // case: `Write1
	 `Complete: begin eop_ <= `Enable_;
	 breq_ <= `Disable_;
	 state <= `Wait;
	    end
	  endcase // case (state)
	 `BURST_MEM_IO:
	  case (state)
	 `Wait: begin  if (dreq_ == `Enable_) begin
	    breq_ <= `Enable_;
	    count <= 4;
	    state <= `Read1;
	    
	 end
	    dsaddreg <= dsaddr;
	    ddaddreg <= ddaddr;
	    
	 eop_ <= `Disable_;
	    end
	 `Read1:begin 
if(count == 4) begin
   dsaddreg <= dsaddr;
	    ddaddreg <= ddaddr;
   end
if (bgrt_ == `Enable_ ) begin
	   addr <= dsaddreg;
            rw_ <= `Read;	 
	   state <= `Write1;
	   count <= count-1;
end
	    end
	 `Write1:begin addr <= ddaddreg;
	 rw_ <= `Write;
	 odata <= idata;
	 if(count != 0) begin
	    dsaddreg <= dsaddreg + 1;
	    state <= `Read1;
	 end else begin
         state <= `Complete;
	 end
	 end // case: `Write1
	    
	 `Complete: begin eop_ <= `Enable_;
	 breq_ <= `Disable_;
	 state <= `Wait;
	 end
	    
	  endcase // case (state)
	 `BURST_IO_MEM:
	  case (state)
	 `Wait: begin if (dreq_ == `Enable_) begin
	    breq_ <= `Enable_;
	    count <= 4;
	    dsaddreg <= dsaddr;
	    ddaddreg <= ddaddr;
	    state <= `Read1;
	 end
	 eop_ <= `Disable_;
	 end
	    
	 `Read1: if (bgrt_ == `Enable_ ) begin
	   addr <= dsaddreg;
            rw_ <= `Read;	 
	   state <= `Write1;
	    count <= count-1;
		  end
       
	 `Write1:begin addr <= ddaddreg;
	 rw_ <= `Write;
	 odata <= idata;
	 if(count != 0) begin
	    ddaddreg <= ddaddreg + 1;
	    state <= `Read1;
	 end else begin
         state <= `Complete;
	 end
	 end // case: `Write1
	    
	 `Complete: begin eop_ <= `Enable_;
	 breq_ <= `Disable_;
	 state <= `Wait;
	 end
	  endcase // case (state)
	endcase // case (dmode)
     end // else: !if(reset_ == `Enable_)
   end // always @ (posedge clk)
  	  endmodule // dmactr

backup/busarb.v
`timescale 1ns/10ps

`include "define.h"
module busarb(
	      input breq0_, input breq1_, output bgrt0_, output bgrt1_, input reset_, input clk);

   reg 		    busstate;
   assign bgrt0_ = (busstate == `BGRT0) ? `Enable_: `Disable_;
   assign bgrt1_ = (busstate == `BGRT1) ? `Enable_: `Disable_;
   always @ (posedge clk)
     if(reset_ == `Enable_) begin
	busstate <= `BGRT0;
     end else begin
       case (busstate)
	 `BGRT0: if (breq0_ == `Disable_ && breq1_ == `Enable_)
	   busstate <= `BGRT1;
	 `BGRT1: if (breq0_ == `Enable_ && breq1_ == `Disable_)
	   busstate <= `BGRT0;
       endcase // case (state)
     end
endmodule // busarb

backup/timer.v
`include "define.h"
module timer (
	      input [`MEM_ADDR_WIDTH-1:0] addr,
	      input [`DATA_WIDTH-1:0] idata,
	      output [`DATA_WIDTH-1:0] odata,
	      input cs_, input rw_, input clk);

   reg [31:0] 	    count;
   reg 		    en;
   wire 	    clear, start, stop;

   assign clear = (cs_ == `Enable_ && rw_ == `Write && addr == 4 && idata == 1)?`Enable:`Disable;
   assign start = (cs_ == `Enable_ && rw_ == `Write && addr == 4 && idata == 2)?`Enable:`Disable;
   assign stop = (cs_ == `Enable_ && rw_ == `Write && addr == 4 && idata == 4)?`Enable:`Disable;

   always @ (posedge clk)
     if(clear) count <= 0;
     else if (en) count <= count + 1;
   always @ (posedge clk)
     if(start) en <= `Enable;
   always @ (posedge clk)
     if(stop) en <= `Disable;
   assign odata = (addr == 0) ? count[7:0]:
		  (addr == 1) ? count[15:8]:
		  (addr == 2) ? count[23:16]:
		  (addr == 3) ? count[31:24]:0;
endmodule // timer

backup/sram.v
`timescale 1ns/10ps

`include "define.h"
module sram(
	    input [`MEM_ADDR_WIDTH-1:0] addr,
	    input [`DATA_WIDTH-1:0] idata,
	    output [`DATA_WIDTH-1:0] odata,
	    input cs_, input rw_, input clk);

   reg [`DATA_WIDTH-1:0] mem[(1<<`MEM_ADDR_WIDTH)-1:0];
   assign odata = (cs_ == `Enable_ && rw_ == `Read) ? mem[addr]: 0;

   always @ (posedge clk)
     if(cs_ == `Enable_ && rw_ == `Write)
       mem[addr] <= idata;
endmodule // sram

backup/addrdec.v
`timescale 1ns/10ps

`include "define.h"
module addrdec(
	       input [`BUS_ADDR_WIDTH-1:0] addr,
	       output cs0_, output cs1_, output cs2_, output cs3_);
   assign cs0_ = (addr[9:8] == 2'b00) ? `Enable_: `Disable_;
   assign cs1_ = (addr[9:8] == 2'b01) ? `Enable_: `Disable_;
   assign cs2_ = (addr[9:8] == 2'b10) ? `Enable_: `Disable_;
   assign cs3_ = (addr[9:8] == 2'b11) ? `Enable_: `Disable_;
endmodule // addrdec

backup/slaves.v
`timescale 1ns/10ps

`include "define.h"
module slaves (
	    input [`BUS_ADDR_WIDTH-1:0] addr,
	    input [`DATA_WIDTH-1:0] idata,
	    output [`DATA_WIDTH-1:0] odata,
	    input rw_, input reset_, input clk);

   wire [`DATA_WIDTH-1:0] odata0, odata1, odata2;
   wire 		  cs0_, cs1_, cs2_, cs3_;

   addrdec u0 (addr, cs0_, cs1_, cs2_, cs3_);
   sram u1(addr[`MEM_ADDR_WIDTH-1:0], idata, odata0, cs0_, rw_, clk);
   sram u2(addr[`MEM_ADDR_WIDTH-1:0], idata, odata1, cs1_, rw_, clk);
   timer u3(addr[`MEM_ADDR_WIDTH-1:0], idata, odata2, cs2_, rw_, clk);
   
   assign odata = (cs0_ == `Enable_) ? odata0:
		  (cs1_ == `Enable_) ? odata1:
                  (cs2_ == `Enable_) ? odata2:0;
   

endmodule // top

backup/top.v
`include "define.h" 
module top(
	   input [`BUS_ADDR_WIDTH-1:0] addr0,
	   input [`DATA_WIDTH-1:0] idata0,
	   output [`DATA_WIDTH-1:0] odata0,
	   input rw0_, input breq0_, output bgrt0_,

	   input [`BUS_ADDR_WIDTH-1:0] dsaddr,
	   input [`BUS_ADDR_WIDTH-1:0] ddaddr,
	   input [1:0] dmode,
	   input dreq_,
	   output eop_,
	   input reset_, input clk);

   wire [`BUS_ADDR_WIDTH-1:0] addr1;
   wire [`DATA_WIDTH-1:0]     idata1;
   wire [`DATA_WIDTH-1:0]     odata1;
   wire [`DATA_WIDTH-1:0]     odata;
   wire [`BUS_ADDR_WIDTH-1:0] addr;
   wire [`DATA_WIDTH-1:0]     idata;
   wire 		      rw_;
   
   wire 		      rw1_, breq1_, bgrt1_;
   assign odata0 = odata;
   assign odata1 = odata;
   assign addr = (bgrt0_ == `Enable_ && bgrt1_ == `Disable_) ? addr0: addr1;
   assign idata = (bgrt0_ == `Enable_ && bgrt1_ == `Disable_) ? idata0: idata1;
   assign rw_ = (bgrt0_ == `Enable_ && bgrt1_ == `Disable_) ? rw0_: rw1_;
   slaves u0 (addr, idata, odata, rw_, reset_, clk);
   busarb u1(breq0_, breq1_, bgrt0_, bgrt1_, reset_, clk);
   dmactr u2(addr1, idata1, odata1, rw1_, breq1_, bgrt1_, dsaddr, ddaddr, dmode, dreq_,eop_,reset_, clk);
   
endmodule // top

backup/test.v
`timescale 1ns/10ps
`include "define.h"
module test();
   reg[`BUS_ADDR_WIDTH-1:0] addr0;
   reg [`DATA_WIDTH-1:0]    idata0;
   wire [`DATA_WIDTH-1:0]   odata0;
   reg 			    rw0_;
   reg 			    breq0_;
   wire 		    bgrt0_;
   reg [`BUS_ADDR_WIDTH-1:0] dsaddr;
   reg [`BUS_ADDR_WIDTH-1:0] ddaddr;
   reg [1:0] 		     dmode;
   reg 			     dreq_;
   wire		     eop_;
   reg 			    reset_, clk;
   top u0(addr0, idata0, odata0, rw0_, breq0_, bgrt0_, dsaddr, ddaddr, dmode, dreq_, eop_, reset_, clk);
   always begin
      clk <= 1;
      #1;
      clk <= 0;
      #1;
   end
   initial begin
      #1;
      $dumpfile("dump.vcd");
      $dumpvars(0, test.u0);
      reset_ <= `Enable_;
      #5;
      reset_ <= `Enable_;
      #5;
      reset_ <= `Disable_;
      #5;
      
      addr0 <= 10'h150;
      idata0 <= 8'h99;
      rw0_ <= `Write;
      breq0_ <= `Enable_;
      dreq_ <= `Disable_;
      
      #2;
      rw0_ <= `Read;
      addr0 <= 10'h150;
      idata0 <= 0;
      #2;
      $display("processor read and write");
      $display("addr = %h odata = %h", addr0, odata0);
      #2;
      breq0_ <= `Disable_;
      dsaddr <= 10'h150;
      ddaddr <= 10'h160;
      dmode <= `Single;
      dreq_ <= `Enable_;
      #1;
      dreq_ <= `Disable_;
      #2;
      breq0_ <= `Enable_;
      rw0_ <= `Read;
      addr0 <= 10'h160;
      idata0 <= 0;
      #2;
      $display("DMA single mode");
      $display("addr = %h odata = %h", addr0, odata0);
      #5;
      addr0 <= 10'h151;
      idata0 <= 8'h98;
      rw0_ <= `Write;
      breq0_ <= `Enable_;
      dreq_ <= `Disable_;
      #2;
      rw0_ <= `Read;
      addr0 <= 10'h151;
      idata0 <= 0;
      #2;
      $display(" ");
      $display("addr = %h odata = %h", addr0, odata0);
      #2;
      
      addr0 <= 10'h152;
      idata0 <= 8'h97;
      rw0_ <= `Write;
      breq0_ <= `Enable_;
      dreq_ <= `Disable_;
      #2;
      rw0_ <= `Read;
      addr0 <= 10'h152;
      idata0 <= 0;
      #2;
      $display("addr = %h odata = %h", addr0, odata0);
      #2;
      
      addr0 <= 10'h153;
      idata0 <= 8'h96;
      rw0_ <= `Write;
      breq0_ <= `Enable_;
      dreq_ <= `Disable_;
      
      #2;
      rw0_ <= `Read;
      addr0 <= 10'h153;
      idata0 <= 0;
      #2;
      $display("addr = %h odata = %h", addr0, odata0);
      #2;
      addr0 <= 10'h204;
      idata0 <= 8'h4;
      rw0_ <= `Write;
      breq0_ <= `Enable_;
      dreq_ <= `Disable_;
      #2;
      addr0 <= 10'h204;
      idata0 <= 8'h1;
      rw0_ <= `Write;
      breq0_ <= `Enable_;
      dreq_ <= `Disable_;
      #2;
      addr0 <= 10'h170;
      idata0 <= 8'h2;
      rw0_ <= `Write;
      breq0_ <= `Enable_;
      dreq_ <= `Disable_;
      #2;
      rw0_ <= `Read;
      addr0 <= 10'h170;
      idata0 <= 0;
      #2;
      $display("addr = %h odata = %h", addr0, odata0);
      #2;
      addr0 <= 10'h171;
      idata0 <= 8'h5;
      rw0_ <= `Write;
      breq0_ <= `Enable_;
      dreq_ <= `Disable_;
      #2;
      rw0_ <= `Read;
      addr0 <= 10'h171;
      idata0 <= 0;
      #2;
      $display("addr = %h odata = %h", addr0, odata0);
      #2;
      addr0 <= 10'h172;
      idata0 <= 8'h4;
      rw0_ <= `Write;
      breq0_ <= `Enable_;
      dreq_ <= `Disable_;
      #2;
      rw0_ <= `Read;
      addr0 <= 10'h172;
      idata0 <= 0;
      #2;
      $display("addr = %h odata = %h", addr0, odata0);
      #2;
      #2;
      addr0 <= 10'h173;
      idata0 <= 8'h2;
      rw0_ <= `Write;
      breq0_ <= `Enable_;
      dreq_ <= `Disable_;
      
      #2;
      rw0_ <= `Read;
      addr0 <= 10'h173;
      idata0 <= 0;
      #2;
      $display("addr = %h odata = %h", addr0, odata0);
      #2;
      breq0_ <= `Disable_;
      dsaddr <= 10'h150;
      ddaddr <= 10'h160;
      dmode <= `BURST_MEM_MEM;
      dreq_ <= `Enable_;
      #1;
      dreq_ <= `Disable_;
      #2;
      breq0_ <= `Enable_;
      rw0_ <= `Read;
      addr0 <= 10'h160;
      idata0 <= 0;
      #2;
      $display("DMA burst memory to memory(from 150 to 160)");
      $display("addr = %h odata = %h", addr0, odata0);
      #2;
      breq0_ <= `Enable_;
      rw0_ <= `Read;
      addr0 <= 10'h161;
      idata0 <= 0;
      #2;
      $display("addr = %h odata = %h", addr0, odata0);
      #2;
      breq0_ <= `Enable_;
      rw0_ <= `Read;
      addr0 <= 10'h162;
      idata0 <= 0;
      #2;
      $display("addr = %h odata = %h", addr0, odata0);
      #2;
      breq0_ <= `Enable_;
      rw0_ <= `Read;
      addr0 <= 10'h163;
      idata0 <= 0;
      #2;
      $display("addr = %h odata = %h", addr0, odata0);
      #2;
      breq0_ <= `Disable_;
      dsaddr <= 10'h170;
      ddaddr <= 10'h204;
      dmode <= `BURST_MEM_IO;
      dreq_ <= `Enable_;
      #8;
      dreq_ <= `Disable_;
      #2;
      breq0_ <= `Enable_;
      rw0_ <= `Read;
      addr0 <= 10'h200;
      idata0 <= 0;
      #5;
      $display("DMA burst memory to IO(from 170 to 204)");
      $display("addr = %h odata = %h", addr0, odata0);
      #5;
      addr0 <= 10'h204;
      idata0 <= 2;
      rw0_ <= `Write;
      breq0_ <= `Enable_;
      dreq_ <= `Disable_;
      #5;
      breq0_ <= `Disable_;
      dsaddr <= 10'h200;
      ddaddr <= 10'h180;
      dmode <= `BURST_IO_MEM;
      dreq_ <= `Enable_;
      #10;
      dreq_ <= `Disable_;
      #5;
      breq0_ <= `Enable_;
      rw0_ <= `Read;
      addr0 <= 10'h180;
      idata0 <= 0;
      #10;
      $display("DMA burst IO to memory(from 200 to 180");
      $display("addr = %h odata = %h", addr0, odata0);
      #2;
      breq0_ <= `Enable_;
      rw0_ <= `Read;
      addr0 <= 10'h181;
      idata0 <= 0;
      #5;
      $display("addr = %h odata = %h", addr0, odata0);
      #2;
      breq0_ <= `Enable_;
      rw0_ <= `Read;
      addr0 <= 10'h182;
      idata0 <= 0;
      #2;
      $display("addr = %h odata = %h", addr0, odata0);
      #2;
      breq0_ <= `Enable_;
      rw0_ <= `Read;
      addr0 <= 10'h183;
      idata0 <= 0;
      #2;
      $display("addr = %h odata = %h", addr0, odata0);
      #5;
      $finish;
      
   end // initial begin
endmodule // test

backup/dump.vcd
$date
    Jun 19, 2018  15:19:02
$end
$version
    TOOL:	ncsim	06.20-s004
$end
$timescale
    10 ps
$end

$scope module test $end

$scope module u0 $end
$var wire     10 !    addr0 [9:0] $end
$var wire      8 "    idata0 [7:0] $end
$var wire      8 #    odata0 [7:0] $end
$var wire      1 $    rw0_  $end
$var wire      1 %    breq0_  $end
$var wire      1 &    bgrt0_  $end
$var wire     10 '    dsaddr [9:0] $end
$var wire     10 (    ddaddr [9:0] $end
$var wire      2 )    dmode [1:0] $end
$var wire      1 *    dreq_  $end
$var wire      1 +    eop_  $end
$var wire      1 ,    reset_  $end
$var wire      1 -    clk  $end
$var wire     10 .    addr1 [9:0] $end
$var wire      8 /    idata1 [7:0] $end
$var wire      8 #    odata1 [7:0] $end
$var wire      8 0    odata [7:0] $end
$var wire     10 1    addr [9:0] $end
$var wire      8 2    idata [7:0] $end
$var wire      1 3    rw_  $end
$var wire      1 4    rw1_  $end
$var wire      1 5    breq1_  $end
$var wire      1 6    bgrt1_  $end

$scope module u0 $end
$var wire     10 1    addr [9:0] $end
$var wire      8 2    idata [7:0] $end
$var wire      8 0    odata [7:0] $end
$var wire      1 3    rw_  $end
$var wire      1 ,    reset_  $end
$var wire      1 -    clk  $end
$var wire      8 7    odata0 [7:0] $end
$var wire      8 8    odata1 [7:0] $end
$var wire      8 9    odata2 [7:0] $end
$var wire      1 :    cs0_  $end
$var wire      1 ;    cs1_  $end
$var wire      1 <    cs2_  $end
$var wire      1 =    cs3_  $end

$scope module u0 $end
$var wire     10 1    addr [9:0] $end
$var wire      1 :    cs0_  $end
$var wire      1 ;    cs1_  $end
$var wire      1 <    cs2_  $end
$var wire      1 =    cs3_  $end
$upscope $end


$scope module u1 $end
$var wire      8 >    addr [7:0] $end
$var wire      8 2    idata [7:0] $end
$var wire      8 7    odata [7:0] $end
$var wire      1 :    cs_  $end
$var wire      1 3    rw_  $end
$var wire      1 -    clk  $end
$upscope $end


$scope module u2 $end
$var wire      8 >    addr [7:0] $end
$var wire      8 2    idata [7:0] $end
$var wire      8 8    odata [7:0] $end
$var wire      1 ;    cs_  $end
$var wire      1 3    rw_  $end
$var wire      1 -    clk  $end
$upscope $end


$scope module u3 $end
$var wire      8 >    addr [7:0] $end
$var wire      8 2    idata [7:0] $end
$var wire      8 9    odata [7:0] $end
$var wire      1 <    cs_  $end
$var wire      1 3    rw_  $end
$var wire      1 -    clk  $end
$var reg      32 ?    count [31:0] $end
$var reg       1 @    en  $end
$var wire      1 A    clear  $end
$var wire      1 B    start  $end
$var wire      1 C    stop  $end
$upscope $end

$upscope $end


$scope module u1 $end
$var wire      1 %    breq0_  $end
$var wire      1 5    breq1_  $end
$var wire      1 &    bgrt0_  $end
$var wire      1 6    bgrt1_  $end
$var wire      1 ,    reset_  $end
$var wire      1 -    clk  $end
$var reg       1 D    busstate  $end
$upscope $end


$scope module u2 $end
$var reg      10 E    addr [9:0] $end
$var reg       8 F    odata [7:0] $end
$var wire      8 #    idata [7:0] $end
$var reg       1 G    rw_  $end
$var reg       1 H    breq_  $end
$var wire      1 6    bgrt_  $end
$var wire     10 '    dsaddr [9:0] $end
$var wire     10 (    ddaddr [9:0] $end
$var wire      2 )    dmode [1:0] $end
$var wire      1 *    dreq_  $end
$var reg       1 I    eop_  $end
$var wire      1 ,    reset_  $end
$var wire      1 -    clk  $end
$var reg       2 J    state [1:0] $end
$var reg       3 K    count [2:0] $end
$var reg      10 L    dsaddreg [9:0] $end
$var reg      10 M    ddaddreg [9:0] $end
$upscope $end

$upscope $end

$upscope $end

$enddefinitions $end
#100
$dumpvars
bx !
bx "
bx #
x$
x%
x&
bx '
bx (
bx )
x*
x+
0,
0-
bx .
bx /
bx 0
bx 1
bx 2
x3
x4
x5
x6
bx 7
bx 8
bx 9
x:
x;
x<
x=
bx >
bx ?
x@
xA
xB
xC
xD
bx E
bx F
xG
xH
xI
bx J
bx K
bx L
bx M
$end
#200
1-
0D
b0 J
16
0&
#300
0-
#400
1-
#500
0-
#600
1-
#700
0-
#800
1-
#900
0-
#1000
1-
#1100
0-
1,
#1200
1-
#1300
0-
#1400
1-
#1500
0-
#1600
b101010000 !
1-
1*
0%
0$
b10011001 "
b10011001 2
03
b101010000 1
b1010000 >
1=
1<
0;
1:
b0 7
b0 8
0C
0B
0A
b0 0
b0 9
b0 #
#1700
0-
#1800
1-
b0 "
1$
13
b0 2
bx 8
bx 0
bx #
b10011001 8
b10011001 0
b10011001 #
#1900
0-
#2000
1-
#2100
0-
#2200
1-
0*
b0 )
b101100000 (
b101010000 '
1%
0H
1I
1+
05
b1 J
#2300
0-
1*
#2400
1-
1D
06
1&
bx 1
bx 2
x3
bx00xx00x 8
bx >
x=
x<
x;
x:
bx 7
bx 8
xC
xB
xA
bx 9
bx00xx00x 0
bx00xx00x #
bx 0
bx #
#2500
b101100000 !
0-
0%
#2600
1-
b101010000 E
1G
b10 J
14
b101010000 .
b101010000 1
13
0C
0B
0A
b1010000 >
1=
1<
0;
1:
b0 7
b10011001 8
b0 9
b10011001 0
b10011001 #
#2700
0-
#2800
1-
b101100000 E
0G
b10011001 F
b11 J
b10011001 /
04
b101100000 .
b101100000 1
03
b10011001 2
b0 8
b1100000 >
b0 0
b0 #
#2900
0-
#3000
1-
0I
1H
b0 J
15
0+
#3100
0-
#3200
b101010001 !
1-
0$
b10011000 "
1I
1+
0D
16
0&
b101010001 1
b10011000 2
b1010001 >
#3300
0-
#3400
1-
b0 "
1$
13
b0 2
bx 8
bx 0
bx #
b10011000 8
b10011000 0
b10011000 #
#3500
0-
#3600
1-
#3700
0-
#3800
b101010010 !
1-
0$
b10010111 "
b10010111 2
03
b101010010 1
b1010010 >
b0 8
b0 0
b0 #
#3900
0-
#4000
1-
b0 "
1$
13
b0 2
bx 8
bx 0
bx #
b10010111 8
b10010111 0
b10010111 #
#4100
0-
#4200
1-
#4300
0-
#4400
b101010011 !
1-
0$
b10010110 "
b10010110 2
03
b101010011 1
b1010011 >
b0 8
b0 0
b0 #
#4500
0-
#4600
1-
b0 "
1$
13
b0 2
bx 8
bx 0
bx #
b10010110 8
b10010110 0
b10010110 #
#4700
0-
#4800
1-
#4900
0-
#5000
b1000000100 !
1-
0$
b100 "
b100 2
03
b1000000100 1
b100 >
0<
1;
b0 8
b0 0
1C
b0 #
#5100
0-
#5200
1-
b1 "
b1 2
0C
1A
0@
#5300
0-
#5400
b101110000 !
1-
b10 "
b10 2
b101110000 1
b1110000 >
1<
0;
1B
0A
0B
b0 ?
#5500
0-
#5600
1-
b0 "
1$
13
b0 2
bx 8
bx 0
bx #
b10 8
b10 0
b10 #
#5700
0-
#5800
1-
#5900
0-
#6000
b101110001 !
1-
0$
b101 "
b101 2
03
b101110001 1
b1110001 >
b0 8
b0 0
b0 #
#6100
0-
#6200
1-
b0 "
1$
13
b0 2
bx 8
bx 0
bx #
b101 8
b101 0
b101 #
#6300
0-
#6400
1-
#6500
0-
#6600
b101110010 !
1-
0$
b100 "
b100 2
03
b101110010 1
b1110010 >
b0 8
b0 0
b0 #
#6700
0-
#6800
1-
b0 "
1$
13
b0 2
bx 8
bx 0
bx #
b100 8
b100 0
b100 #
#6900
0-
#7000
1-
#7100
0-
#7200
1-
#7300
0-
#7400
b101110011 !
1-
0$
b10 "
b10 2
03
b101110011 1
b1110011 >
b0 8
b0 0
b0 #
#7500
0-
#7600
1-
b0 "
1$
13
b0 2
bx 8
bx 0
bx #
b10 8
b10 0
b10 #
#7700
0-
#7800
1-
#7900
0-
#8000
1-
0*
b1 )
1%
0H
b100 K
b1 J
05
#8100
0-
1*
#8200
1-
1D
b101010000 L
b101100000 M
06
1&
b101100000 1
b10011001 2
03
b0 8
b1100000 >
b0 0
b0 #
#8300
b101100000 !
0-
0%
#8400
1-
b101010000 E
1G
b10 J
b11 K
14
b101010000 .
b101010000 1
13
b10011001 8
b1010000 >
b10011001 0
b10011001 #
#8500
0-
#8600
1-
b101100000 E
0G
b101010001 L
b101100001 M
b1 J
04
b101100000 .
b101100000 1
03
b0 8
b1100000 >
b0 0
b0 #
#8700
b101100001 !
0-
#8800
1-
b101010001 E
1G
b10 J
b10 K
14
b101010001 .
b101010001 1
13
b10011001 8
b1010001 >
b10011000 8
b10011001 0
b10011001 #
b10011000 0
b10011000 #
#8900
0-
#9000
1-
b101100001 E
0G
b10011000 F
b101010010 L
b101100010 M
b1 J
b10011000 /
04
b101100001 .
b101100001 1
03
b10011000 2
b0 8
b1100001 >
b0 0
b0 #
#9100
b101100010 !
0-
#9200
1-
b101010010 E
1G
b10 J
b1 K
14
b101010010 .
b101010010 1
13
b10011000 8
b1010010 >
b10010111 8
b10011000 0
b10011000 #
b10010111 0
b10010111 #
#9300
0-
#9400
1-
b101100010 E
0G
b10010111 F
b101010011 L
b101100011 M
b1 J
b10010111 /
04
b101100010 .
b101100010 1
03
b10010111 2
b0 8
b1100010 >
b0 0
b0 #
#9500
b101100011 !
0-
#9600
1-
b101010011 E
1G
b10 J
b0 K
14
b101010011 .
b101010011 1
13
b10010111 8
b1010011 >
b10010110 8
b10010111 0
b10010111 #
b10010110 0
b10010110 #
#9700
0-
#9800
1-
b101100011 E
0G
b10010110 F
b11 J
b10010110 /
04
b101100011 .
b101100011 1
03
b10010110 2
b0 8
b1100011 >
b0 0
b0 #
#9900
0-
0*
b10 )
b1000000100 (
b101110000 '
1%
#10000
1-
0I
1H
b0 J
15
0+
#10100
0-
#10200
1-
0H
b100 K
b1 J
b101110000 L
b1000000100 M
1I
1+
05
#10300
0-
#10400
1-
b101110000 E
1G
b10 J
b11 K
14
b101110000 .
b101110000 1
13
b10010110 8
b1110000 >
b10 8
b10010110 0
b10010110 #
b10 0
b10 #
#10500
0-
#10600
1-
b1000000100 E
0G
b10 F
b101110001 L
b1 J
b10 /
04
b1000000100 .
b1000000100 1
03
b10 2
b0 8
b100 >
0<
1;
1B
b0 0
b0 #
#10700
0-
1*
#10800
1-
1@
b101110001 E
1G
b10 J
b10 K
14
b101110001 .
b101110001 1
13
0B
b1110001 >
1<
0;
b101 8
b101 0
b101 #
#10900
b1000000000 !
0-
0%
#11000
1-
b1 ?
b1000000100 E
0G
b101 F
b101110010 L
b1 J
b101 /
04
b1000000100 .
b1000000100 1
03
b101 2
b0 8
b100 >
0<
1;
b0 0
b0 #
#11100
0-
#11200
1-
b10 ?
b101110010 E
1G
b10 J
b1 K
14
b101110010 .
b101110010 1
13
b1110010 >
1<
0;
b100 8
b100 0
b100 #
#11300
0-
#11400
1-
b11 ?
b1000000100 E
0G
b100 F
b101110011 L
b1 J
b100 /
04
b1000000100 .
b1000000100 1
03
b100 2
b0 8
b100 >
0<
1;
1C
b0 0
b0 #
#11500
0-
#11600
1-
0@
b100 ?
b101110011 E
1G
b10 J
b0 K
14
b101110011 .
b101110011 1
13
0C
b1110011 >
1<
0;
b10 8
b10 0
b10 #
#11700
0-
#11800
1-
b1000000100 E
0G
b10 F
b11 J
b10 /
04
b1000000100 .
b1000000100 1
03
b10 2
b0 8
b100 >
0<
1;
1B
b0 0
b0 #
#11900
b1000000100 !
0-
0$
b10 "
#12000
1-
1@
0I
1H
b0 J
15
0+
#12100
0-
#12200
1-
b101 ?
0D
b101110000 L
1I
16
0&
1+
#12300
0-
#12400
1-
0*
b11 )
b110000000 (
b1000000000 '
1%
b110 ?
0H
b100 K
b1000000000 L
b110000000 M
b1 J
05
#12500
0-
#12600
1-
b111 ?
1D
06
1&
#12700
0-
#12800
1-
b1000 ?
b1000000000 E
1G
b10 J
b11 K
14
b1000000000 .
b1000000000 1
13
0B
b0 >
b1000 9
b1000 0
b1000 #
#12900
0-
#13000
1-
b1001 ?
b110000000 E
0G
b1000 F
b110000001 M
b1 J
b1001 9
b1000 /
04
b110000000 .
b110000000 1
03
b1000 2
b1001 0
b1001 #
b10000000 >
1<
0;
b0 0
b0 9
b0 #
#13100
0-
#13200
1-
b1010 ?
b1000000000 E
1G
b10 J
b10 K
14
b1000000000 .
b1000000000 1
13
b1000 8
b0 >
0<
1;
b0 8
b1010 9
b1010 0
b1010 #
#13300
0-
#13400
1-
1*
b1011 ?
b110000001 E
0G
b1010 F
b110000010 M
b1 J
b1011 9
b1010 /
04
b110000001 .
b110000001 1
03
b1010 2
b1011 0
b1011 #
b10000001 >
1<
0;
b0 0
b0 9
b0 #
#13500
0-
#13600
1-
b1100 ?
b1000000000 E
1G
b10 J
b1 K
14
b1000000000 .
b1000000000 1
13
b1010 8
b0 >
0<
1;
b0 8
b1100 9
b1100 0
b1100 #
#13700
0-
#13800
1-
b1101 ?
b110000010 E
0G
b1100 F
b110000011 M
b1 J
b1101 9
b1100 /
04
b110000010 .
b110000010 1
03
b1100 2
b1101 0
b1101 #
b10000010 >
1<
0;
b0 0
b0 9
b0 #
#13900
b110000000 !
0-
b0 "
1$
0%
#14000
1-
b1110 ?
b1000000000 E
1G
b10 J
b0 K
14
b1000000000 .
b1000000000 1
13
b1100 8
b0 >
0<
1;
b0 8
b1110 9
b1110 0
b1110 #
#14100
0-
#14200
1-
b1111 ?
b110000011 E
0G
b1110 F
b11 J
b1111 9
b1110 /
04
b110000011 .
b110000011 1
03
b1110 2
b1111 0
b1111 #
b10000011 >
1<
0;
b0 0
b0 9
b0 #
#14300
0-
#14400
1-
b10000 ?
0I
1H
b0 J
15
0+
#14500
0-
#14600
1-
b10001 ?
0D
1I
16
0&
1+
b110000000 1
b0 2
13
b1110 8
b10000000 >
b1000 8
b1110 0
b1110 #
b1000 0
b1000 #
#14700
0-
#14800
1-
b10010 ?
#14900
0-
#15000
1-
b10011 ?
#15100
b110000001 !
0-
b110000001 1
b10000001 >
b1010 8
b1010 0
b1010 #
#15200
1-
b10100 ?
#15300
0-
#15400
1-
b10101 ?
#15500
0-
#15600
1-
b10110 ?
#15700
0-
#15800
b110000010 !
1-
b110000010 1
b10000010 >
b1100 8
b1100 0
b1100 #
b10111 ?
#15900
0-
#16000
1-
b11000 ?
#16100
0-
