05/ADDI/mips.v
//-------------------------------------------------------
// mips.v
// Max Yi (byyi@hmc.edu) and David_Harris@hmc.edu 12/9/03
// Model of subset of MIPS processor described in Ch 1
//-------------------------------------------------------

// simplified MIPS processor
module mips #(parameter WIDTH = 8, REGBITS = 3)
             (input              clk, reset, 
              input  [WIDTH-1:0] memdata, 
              output             memread, memwrite, 
              output [WIDTH-1:0] adr, writedata);

   wire [31:0] instr;
   wire        zero, alusrca, memtoreg, iord, pcen, regwrite, regdst;
   wire [1:0]  aluop,pcsource,alusrcb;
   wire [3:0]  irwrite;
   wire [2:0]  alucont;

   controller  cont(clk, reset, instr[31:26], zero, memread, memwrite, 
                    alusrca, memtoreg, iord, pcen, regwrite, regdst,
                    pcsource, alusrcb, aluop, irwrite);
   alucontrol  ac(aluop, instr[5:0], alucont);
   datapath    #(WIDTH, REGBITS) 
               dp(clk, reset, memdata, alusrca, memtoreg, iord, pcen,
                  regwrite, regdst, pcsource, alusrcb, irwrite, alucont,
                  zero, instr, adr, writedata);
endmodule

module controller(input clk, reset, 
                  input      [5:0] op, 
                  input            zero, 
                  output reg       memread, memwrite, alusrca, memtoreg, iord, 
                  output           pcen, 
                  output reg       regwrite, regdst, 
                  output reg [1:0] pcsource, alusrcb, aluop, 
                  output reg [3:0] irwrite);

   parameter   FETCH1  =  4'b0001;
   parameter   FETCH2  =  4'b0010;
   parameter   FETCH3  =  4'b0011;
   parameter   FETCH4  =  4'b0100;
   parameter   DECODE  =  4'b0101;
   parameter   MEMADR  =  4'b0110;
   parameter   LBRD    =  4'b0111;
   parameter   LBWR    =  4'b1000;
   parameter   SBWR    =  4'b1001;
   parameter   RTYPEEX =  4'b1010;
   parameter   RTYPEWR =  4'b1011;
   parameter   BEQEX   =  4'b1100;
   parameter   JEX     =  4'b1101;
   parameter   ADDIEX  =  4'b1110;
   parameter   ADDIWB  =  4'b1111;

   parameter   LB      =  6'b100000;
   parameter   SB      =  6'b101000;
   parameter   RTYPE   =  6'b0;
   parameter   BEQ     =  6'b000100;
   parameter   J       =  6'b000010;
   parameter   ADDI    =  6'b001000;

   reg [3:0] state, nextstate;
   reg       pcwrite, pcwritecond;

   // state register
   always @(posedge clk)
      if(reset) state <= FETCH1;
      else state <= nextstate;

   // next state logic
   always @(*)
      begin
         case(state)
            FETCH1:  nextstate <= FETCH2;
            FETCH2:  nextstate <= FETCH3;
            FETCH3:  nextstate <= FETCH4;
            FETCH4:  nextstate <= DECODE;
            DECODE:  case(op)
                        LB:      nextstate <= MEMADR;
                        SB:      nextstate <= MEMADR;
                        RTYPE:   nextstate <= RTYPEEX;
                        BEQ:     nextstate <= BEQEX;
                        J:       nextstate <= JEX;
			ADDI:    nextstate <= ADDIEX;
                        default: nextstate <= FETCH1; // should never happen
                     endcase
            MEMADR:  case(op)
                        LB:      nextstate <= LBRD;
                        SB:      nextstate <= SBWR;
                        default: nextstate <= FETCH1; // should never happen
                     endcase
            LBRD:    nextstate <= LBWR;
            LBWR:    nextstate <= FETCH1;
            SBWR:    nextstate <= FETCH1;
            RTYPEEX: nextstate <= RTYPEWR;
            RTYPEWR: nextstate <= FETCH1;
            BEQEX:   nextstate <= FETCH1;
            JEX:     nextstate <= FETCH1;
	    ADDIEX:  nextstate <= ADDIWB;

            default: nextstate <= FETCH1; // should never happen
         endcase
      end

   always @(*)
      begin
            // set all outputs to zero, then conditionally assert just the appropriate ones
            irwrite <= 4'b0000;
            pcwrite <= 0; pcwritecond <= 0;
            regwrite <= 0; regdst <= 0;
            memread <= 0; memwrite <= 0;
            alusrca <= 0; alusrcb <= 2'b00; aluop <= 2'b00;
            pcsource <= 2'b00;
            iord <= 0; memtoreg <= 0;
            case(state)
               FETCH1: 
                  begin
                     memread <= 1; 
                     irwrite <= 4'b1000; 
                     alusrcb <= 2'b01; 
                     pcwrite <= 1;
                  end
               FETCH2: 
                  begin
                     memread <= 1;
                     irwrite <= 4'b0100;
                     alusrcb <= 2'b01;
                     pcwrite <= 1;
                  end
               FETCH3:
                  begin
                     memread <= 1;
                     irwrite <= 4'b0010;
                     alusrcb <= 2'b01;
                     pcwrite <= 1;
                  end
               FETCH4:
                  begin
                     memread <= 1;
                     irwrite <= 4'b0001;
                     alusrcb <= 2'b01;
                     pcwrite <= 1;
                  end
               DECODE: alusrcb <= 2'b11;
               MEMADR:
                  begin
                     alusrca <= 1;
                     alusrcb <= 2'b10;
                  end
               LBRD:
                  begin
                     memread <= 1;
                     iord    <= 1;
                  end
               LBWR:
                  begin
                     regwrite <= 1;
                     memtoreg <= 1;
                  end
               SBWR:
                  begin
                     memwrite <= 1;
                     iord     <= 1;
                  end
               RTYPEEX: 
                  begin
                     alusrca <= 1;
                     aluop   <= 2'b10;
                  end
               RTYPEWR:
                  begin
                     regdst   <= 1;
                     regwrite <= 1;
                  end
               BEQEX:
                  begin
                     alusrca     <= 1;
                     aluop       <= 2'b01;
                     pcwritecond <= 1;
                     pcsource    <= 2'b01;
                  end
               JEX:
                  begin
                     pcwrite  <= 1;
                     pcsource <= 2'b10;
                  end
	       ADDIEX:
		  begin
		     alusrca <= 1;
		     alusrcb <= 2'b10;
		     aluop   <= 2'b00;
   		  end
		ADDIWB:
		  begin
		     regdst <= 0;
		     regwrite <= 1;
		     memtoreg <= 0;
		  end
         endcase
      end
   assign pcen = pcwrite | (pcwritecond & zero); // program counter enable
endmodule

module alucontrol(input      [1:0] aluop, 
                  input      [5:0] funct, 
                  output reg [2:0] alucont);

   always @(*)
      case(aluop)
         2'b00: alucont <= 3'b010;  // add for lb/sb/addi
         2'b01: alucont <= 3'b110;  // sub (for beq)
         default: case(funct)       // R-Type instructions
                     6'b100000: alucont <= 3'b010; // add (for add)
                     6'b100010: alucont <= 3'b110; // subtract (for sub)
                     6'b100100: alucont <= 3'b000; // logical and (for and)
                     6'b100101: alucont <= 3'b001; // logical or (for or)
                     6'b101010: alucont <= 3'b111; // set on less (for slt)
                     default:   alucont <= 3'b101; // should never happen
                  endcase
      endcase
endmodule

module datapath #(parameter WIDTH = 8, REGBITS = 3)
                 (input              clk, reset, 
                  input  [WIDTH-1:0] memdata, 
                  input              alusrca, memtoreg, iord, pcen, regwrite, regdst,
                  input  [1:0]       pcsource, alusrcb, 
                  input  [3:0]       irwrite, 
                  input  [2:0]       alucont, 
                  output             zero, 
                  output [31:0]      instr, 
                  output [WIDTH-1:0] adr, writedata);

   // the size of the parameters must be changed to match the WIDTH parameter
   parameter CONST_ZERO = 8'b0;
   parameter CONST_ONE =  8'b1;

   wire [REGBITS-1:0] ra1, ra2, wa;
   wire [WIDTH-1:0]   pc, nextpc, md, rd1, rd2, wd, a, src1, src2, aluresult,
                          aluout, constx4;

   // shift left constant field by 2
   assign constx4 = {instr[WIDTH-3:0],2'b00};

   // register file address fields
   assign ra1 = instr[REGBITS+20:21];
   assign ra2 = instr[REGBITS+15:16];
   mux2       #(REGBITS) regmux(instr[REGBITS+15:16], instr[REGBITS+10:11], regdst, wa);

   // independent of bit width, load instruction into four 8-bit registers over four cycles
   flopen     #(8)      ir0(clk, irwrite[0], memdata[7:0], instr[7:0]);
   flopen     #(8)      ir1(clk, irwrite[1], memdata[7:0], instr[15:8]);
   flopen     #(8)      ir2(clk, irwrite[2], memdata[7:0], instr[23:16]);
   flopen     #(8)      ir3(clk, irwrite[3], memdata[7:0], instr[31:24]);

   // datapath
   flopenr    #(WIDTH)  pcreg(clk, reset, pcen, nextpc, pc);
   flop       #(WIDTH)  mdr(clk, memdata, md);
   flop       #(WIDTH)  areg(clk, rd1, a);	
   flop       #(WIDTH)  wrd(clk, rd2, writedata);
   flop       #(WIDTH)  res(clk, aluresult, aluout);
   mux2       #(WIDTH)  adrmux(pc, aluout, iord, adr);
   mux2       #(WIDTH)  src1mux(pc, a, alusrca, src1);
   mux4       #(WIDTH)  src2mux(writedata, CONST_ONE, instr[WIDTH-1:0], 
                                constx4, alusrcb, src2);
   mux4       #(WIDTH)  pcmux(aluresult, aluout, constx4, CONST_ZERO, pcsource, nextpc);
   mux2       #(WIDTH)  wdmux(aluout, md, memtoreg, wd);
   regfile    #(WIDTH,REGBITS) rf(clk, regwrite, ra1, ra2, wa, wd, rd1, rd2);
   alu        #(WIDTH) alunit(src1, src2, alucont, aluresult);
   zerodetect #(WIDTH) zd(aluresult, zero);
endmodule

module alu #(parameter WIDTH = 8)
            (input      [WIDTH-1:0] a, b, 
             input      [2:0]       alucont, 
             output reg [WIDTH-1:0] result);

   wire     [WIDTH-1:0] b2, sum, slt;

   assign b2 = alucont[2] ? ~b:b; 
   assign sum = a + b2 + alucont[2];
   // slt should be 1 if most significant bit of sum is 1
   assign slt = sum[WIDTH-1];

   always@(*)
      case(alucont[1:0])
         2'b00: result <= a & b;
         2'b01: result <= a | b;
         2'b10: result <= sum;
         2'b11: result <= slt;
      endcase
endmodule

module regfile #(parameter WIDTH = 8, REGBITS = 3)
                (input                clk, 
                 input                regwrite, 
                 input  [REGBITS-1:0] ra1, ra2, wa, 
                 input  [WIDTH-1:0]   wd, 
                 output [WIDTH-1:0]   rd1, rd2);

   reg  [WIDTH-1:0] RAM [(1<<REGBITS)-1:0];

   // three ported register file
   // read two ports combinationally
   // write third port on rising edge of clock
   // register 0 hardwired to 0
   always @(posedge clk)
      if (regwrite) RAM[wa] <= wd;	

   assign rd1 = ra1 ? RAM[ra1] : 0;
   assign rd2 = ra2 ? RAM[ra2] : 0;
endmodule

module zerodetect #(parameter WIDTH = 8)
                   (input [WIDTH-1:0] a, 
                    output            y);

   assign y = (a==0);
endmodule	

module flop #(parameter WIDTH = 8)
             (input                  clk, 
              input      [WIDTH-1:0] d, 
              output reg [WIDTH-1:0] q);

   always @(posedge clk)
      q <= d;
endmodule

module flopen #(parameter WIDTH = 8)
               (input                  clk, en,
                input      [WIDTH-1:0] d, 
                output reg [WIDTH-1:0] q);

   always @(posedge clk)
      if (en) q <= d;
endmodule

module flopenr #(parameter WIDTH = 8)
                (input                  clk, reset, en,
                 input      [WIDTH-1:0] d, 
                 output reg [WIDTH-1:0] q);
 
   always @(posedge clk)
      if      (reset) q <= 0;
      else if (en)    q <= d;
endmodule

module mux2 #(parameter WIDTH = 8)
             (input  [WIDTH-1:0] d0, d1, 
              input              s, 
              output [WIDTH-1:0] y);

   assign y = s ? d1 : d0; 
endmodule

module mux4 #(parameter WIDTH = 8)
             (input      [WIDTH-1:0] d0, d1, d2, d3,
              input      [1:0]       s, 
              output reg [WIDTH-1:0] y);

   always @(*)
      case(s)
         2'b00: y <= d0;
         2'b01: y <= d1;
         2'b10: y <= d2;
         2'b11: y <= d3;
      endcase
endmodule

05/ADDI/fibtest.v
//-------------------------------------------------------
// mips.v
// Max Yi (byyi@hmc.edu) and David_Harris@hmc.edu 12/9/03
// Model of subset of MIPS processor described in Ch 1
//-------------------------------------------------------
`timescale 1ns/100ps

// top level design for testing
module top #(parameter WIDTH = 8, REGBITS = 3)();

   reg                 clk;
   reg                 reset;
   wire                memread, memwrite;
   wire    [WIDTH-1:0] adr, writedata;
   wire    [WIDTH-1:0] memdata;

   // 5nsec --> 200MHz
   parameter STEP = 5.0;

   // instantiate devices to be tested
   //mips #(WIDTH,REGBITS) dut(clk, reset, memdata, memread, memwrite, adr, writedata);
   mips dut(clk, reset, memdata, memread, memwrite, adr, writedata);

   // external memory for code and data
   exmemory #(WIDTH) exmem(clk, memwrite, adr, writedata, memdata);

   // initialize test
   initial
      begin
         clk <= 0; reset <= 1; # 22; reset <= 0;
         // dump waveform
         $dumpfile("dump.vcd");
         $dumpvars(0, top.dut);
         // stop at 1,000 cycles
         #(STEP*1000);
         $finish;
      end

   // generate clock to sequence tests
   always #(STEP/2)
      begin
         clk <= ~clk;
      end

   always@(negedge clk)
      begin
         if(memwrite) begin
            $display("Data [%d] is stored in Address [%d]", writedata, adr);
            if(adr == 255 & writedata == 13) begin
               $display("Simulation completely successful");
               $finish;
            end else begin
               $display("Simulation failed");
               $finish;
            end
        end
      end
endmodule

// external memory accessed by MIPS
module exmemory #(parameter WIDTH = 8)
                 (clk, memwrite, adr, writedata, memdata);

   input                  clk;
   input                  memwrite;
   input      [WIDTH-1:0] adr, writedata;
   output reg [WIDTH-1:0] memdata;

   reg  [31:0] RAM [(1<<WIDTH-2)-1:0];
   wire [31:0] word;

   initial
      begin
         $readmemh("fibtest.dat", RAM);
      end

   // read and write bytes from 32-bit word
   always @(posedge clk)
      if(memwrite) 
         case (adr[1:0])
            2'b00: RAM[adr>>2][7:0] <= writedata;
            2'b01: RAM[adr>>2][15:8] <= writedata;
            2'b10: RAM[adr>>2][23:16] <= writedata;
            2'b11: RAM[adr>>2][31:24] <= writedata;
         endcase

   assign word = RAM[adr>>2];
   always @(*)
      case (adr[1:0])
         2'b00: memdata <= word[31:24];
         2'b01: memdata <= word[23:16];
         2'b10: memdata <= word[15:8];
         2'b11: memdata <= word[7:0];
      endcase
endmodule

05/dump.vcd
$date
    May 11, 2018  20:07:29
$end
$version
    TOOL:	ncsim	06.20-s004
$end
$timescale
    100 ps
$end

$scope module top $end

$scope module dut $end
$var parameter 32 !    WIDTH  $end
$var parameter 32 "    REGBITS  $end
$var wire      1 #    clk  $end
$var wire      1 $    reset  $end
$var wire      8 %    memdata [7:0] $end
$var wire      1 &    memread  $end
$var wire      1 '    memwrite  $end
$var wire      8 (    adr [7:0] $end
$var wire      8 )    writedata [7:0] $end
$var wire      1 *    instr [31] $end
$var wire      1 +    instr [30] $end
$var wire      1 ,    instr [29] $end
$var wire      1 -    instr [28] $end
$var wire      1 .    instr [27] $end
$var wire      1 /    instr [26] $end
$var wire      1 0    instr [25] $end
$var wire      1 1    instr [24] $end
$var wire      1 2    instr [23] $end
$var wire      1 3    instr [22] $end
$var wire      1 4    instr [21] $end
$var wire      1 5    instr [20] $end
$var wire      1 6    instr [19] $end
$var wire      1 7    instr [18] $end
$var wire      1 8    instr [17] $end
$var wire      1 9    instr [16] $end
$var wire      1 :    instr [15] $end
$var wire      1 ;    instr [14] $end
$var wire      1 <    instr [13] $end
$var wire      1 =    instr [12] $end
$var wire      1 >    instr [11] $end
$var wire      1 ?    instr [10] $end
$var wire      1 @    instr [9] $end
$var wire      1 A    instr [8] $end
$var wire      1 B    instr [7] $end
$var wire      1 C    instr [6] $end
$var wire      1 D    instr [5] $end
$var wire      1 E    instr [4] $end
$var wire      1 F    instr [3] $end
$var wire      1 G    instr [2] $end
$var wire      1 H    instr [1] $end
$var wire      1 I    instr [0] $end
$var wire      1 J    zero  $end
$var wire      1 K    alusrca  $end
$var wire      1 L    memtoreg  $end
$var wire      1 M    iord  $end
$var wire      1 N    pcen  $end
$var wire      1 O    regwrite  $end
$var wire      1 P    regdst  $end
$var wire      2 Q    aluop [1:0] $end
$var wire      2 R    pcsource [1:0] $end
$var wire      2 S    alusrcb [1:0] $end
$var wire      1 T    irwrite [3] $end
$var wire      1 U    irwrite [2] $end
$var wire      1 V    irwrite [1] $end
$var wire      1 W    irwrite [0] $end
$var wire      3 X    alucont [2:0] $end

$scope module cont $end
$var wire      1 #    clk  $end
$var wire      1 $    reset  $end
$var wire      1 *    op [5] $end
$var wire      1 +    op [4] $end
$var wire      1 ,    op [3] $end
$var wire      1 -    op [2] $end
$var wire      1 .    op [1] $end
$var wire      1 /    op [0] $end
$var wire      1 J    zero  $end
$var reg       1 Y    memread  $end
$var reg       1 Z    memwrite  $end
$var reg       1 [    alusrca  $end
$var reg       1 \    memtoreg  $end
$var reg       1 ]    iord  $end
$var wire      1 N    pcen  $end
$var reg       1 ^    regwrite  $end
$var reg       1 _    regdst  $end
$var reg       2 `    pcsource [1:0] $end
$var reg       2 a    alusrcb [1:0] $end
$var reg       2 b    aluop [1:0] $end
$var reg       4 c    irwrite [3:0] $end
$var parameter  4 d    FETCH1  $end
$var parameter  4 e    FETCH2  $end
$var parameter  4 f    FETCH3  $end
$var parameter  4 g    FETCH4  $end
$var parameter  4 h    DECODE  $end
$var parameter  4 i    MEMADR  $end
$var parameter  4 j    LBRD  $end
$var parameter  4 k    LBWR  $end
$var parameter  4 l    SBWR  $end
$var parameter  4 m    RTYPEEX  $end
$var parameter  4 n    RTYPEWR  $end
$var parameter  4 o    BEQEX  $end
$var parameter  4 p    JEX  $end
$var parameter  6 q    LB  $end
$var parameter  6 r    SB  $end
$var parameter  6 s    RTYPE  $end
$var parameter  6 t    BEQ  $end
$var parameter  6 u    J  $end
$var reg       4 v    state [3:0] $end
$var reg       4 w    nextstate [3:0] $end
$var reg       1 x    pcwrite  $end
$var reg       1 y    pcwritecond  $end
$upscope $end


$scope module ac $end
$var wire      2 Q    aluop [1:0] $end
$var wire      1 D    funct [5] $end
$var wire      1 E    funct [4] $end
$var wire      1 F    funct [3] $end
$var wire      1 G    funct [2] $end
$var wire      1 H    funct [1] $end
$var wire      1 I    funct [0] $end
$var reg       3 z    alucont [2:0] $end
$upscope $end


$scope module dp $end
$var parameter 32 {    WIDTH  $end
$var parameter 32 |    REGBITS  $end
$var wire      1 #    clk  $end
$var wire      1 $    reset  $end
$var wire      8 %    memdata [7:0] $end
$var wire      1 K    alusrca  $end
$var wire      1 L    memtoreg  $end
$var wire      1 M    iord  $end
$var wire      1 N    pcen  $end
$var wire      1 O    regwrite  $end
$var wire      1 P    regdst  $end
$var wire      2 R    pcsource [1:0] $end
$var wire      2 S    alusrcb [1:0] $end
$var wire      1 T    irwrite [3] $end
$var wire      1 U    irwrite [2] $end
$var wire      1 V    irwrite [1] $end
$var wire      1 W    irwrite [0] $end
$var wire      3 X    alucont [2:0] $end
$var wire      1 J    zero  $end
$var wire      1 *    instr [31] $end
$var wire      1 +    instr [30] $end
$var wire      1 ,    instr [29] $end
$var wire      1 -    instr [28] $end
$var wire      1 .    instr [27] $end
$var wire      1 /    instr [26] $end
$var wire      1 0    instr [25] $end
$var wire      1 1    instr [24] $end
$var wire      1 2    instr [23] $end
$var wire      1 3    instr [22] $end
$var wire      1 4    instr [21] $end
$var wire      1 5    instr [20] $end
$var wire      1 6    instr [19] $end
$var wire      1 7    instr [18] $end
$var wire      1 8    instr [17] $end
$var wire      1 9    instr [16] $end
$var wire      1 :    instr [15] $end
$var wire      1 ;    instr [14] $end
$var wire      1 <    instr [13] $end
$var wire      1 =    instr [12] $end
$var wire      1 >    instr [11] $end
$var wire      1 ?    instr [10] $end
$var wire      1 @    instr [9] $end
$var wire      1 A    instr [8] $end
$var wire      1 B    instr [7] $end
$var wire      1 C    instr [6] $end
$var wire      1 D    instr [5] $end
$var wire      1 E    instr [4] $end
$var wire      1 F    instr [3] $end
$var wire      1 G    instr [2] $end
$var wire      1 H    instr [1] $end
$var wire      1 I    instr [0] $end
$var wire      8 (    adr [7:0] $end
$var wire      8 )    writedata [7:0] $end
$var parameter  8 }    CONST_ZERO  $end
$var parameter  8 ~    CONST_ONE  $end
$var wire      3 !!   ra1 [2:0] $end
$var wire      3 "!   ra2 [2:0] $end
$var wire      3 #!   wa [2:0] $end
$var wire      8 $!   pc [7:0] $end
$var wire      8 %!   nextpc [7:0] $end
$var wire      8 &!   md [7:0] $end
$var wire      8 '!   rd1 [7:0] $end
$var wire      8 (!   rd2 [7:0] $end
$var wire      8 )!   wd [7:0] $end
$var wire      8 *!   a [7:0] $end
$var wire      8 +!   src1 [7:0] $end
$var wire      8 ,!   src2 [7:0] $end
$var wire      8 -!   aluresult [7:0] $end
$var wire      8 .!   aluout [7:0] $end
$var wire      8 /!   constx4 [7:0] $end

$scope module regmux $end
$var parameter 32 0!   WIDTH  $end
$var wire      1 7    d0 [2] $end
$var wire      1 8    d0 [1] $end
$var wire      1 9    d0 [0] $end
$var wire      1 <    d1 [2] $end
$var wire      1 =    d1 [1] $end
$var wire      1 >    d1 [0] $end
$var wire      1 P    s  $end
$var wire      3 #!   y [2:0] $end
$upscope $end


$scope module ir0 $end
$var parameter 32 1!   WIDTH  $end
$var wire      1 #    clk  $end
$var wire      1 W    en  $end
$var wire      8 %    d [7:0] $end
$var reg       8 2!   q [7:0] $end
$upscope $end


$scope module ir1 $end
$var parameter 32 3!   WIDTH  $end
$var wire      1 #    clk  $end
$var wire      1 V    en  $end
$var wire      8 %    d [7:0] $end
$var reg       8 4!   q [7:0] $end
$upscope $end


$scope module ir2 $end
$var parameter 32 5!   WIDTH  $end
$var wire      1 #    clk  $end
$var wire      1 U    en  $end
$var wire      8 %    d [7:0] $end
$var reg       8 6!   q [7:0] $end
$upscope $end


$scope module ir3 $end
$var parameter 32 7!   WIDTH  $end
$var wire      1 #    clk  $end
$var wire      1 T    en  $end
$var wire      8 %    d [7:0] $end
$var reg       8 8!   q [7:0] $end
$upscope $end


$scope module pcreg $end
$var parameter 32 9!   WIDTH  $end
$var wire      1 #    clk  $end
$var wire      1 $    reset  $end
$var wire      1 N    en  $end
$var wire      8 %!   d [7:0] $end
$var reg       8 :!   q [7:0] $end
$upscope $end


$scope module mdr $end
$var parameter 32 ;!   WIDTH  $end
$var wire      1 #    clk  $end
$var wire      8 %    d [7:0] $end
$var reg       8 <!   q [7:0] $end
$upscope $end


$scope module areg $end
$var parameter 32 =!   WIDTH  $end
$var wire      1 #    clk  $end
$var wire      8 '!   d [7:0] $end
$var reg       8 >!   q [7:0] $end
$upscope $end


$scope module wrd $end
$var parameter 32 ?!   WIDTH  $end
$var wire      1 #    clk  $end
$var wire      8 (!   d [7:0] $end
$var reg       8 @!   q [7:0] $end
$upscope $end


$scope module res $end
$var parameter 32 A!   WIDTH  $end
$var wire      1 #    clk  $end
$var wire      8 -!   d [7:0] $end
$var reg       8 B!   q [7:0] $end
$upscope $end


$scope module adrmux $end
$var parameter 32 C!   WIDTH  $end
$var wire      8 $!   d0 [7:0] $end
$var wire      8 .!   d1 [7:0] $end
$var wire      1 M    s  $end
$var wire      8 (    y [7:0] $end
$upscope $end


$scope module src1mux $end
$var parameter 32 D!   WIDTH  $end
$var wire      8 $!   d0 [7:0] $end
$var wire      8 *!   d1 [7:0] $end
$var wire      1 K    s  $end
$var wire      8 +!   y [7:0] $end
$upscope $end


$scope module src2mux $end
$var parameter 32 E!   WIDTH  $end
$var wire      8 )    d0 [7:0] $end
$var wire      8 F!   d1 [7:0] $end
$var wire      1 B    d2 [7] $end
$var wire      1 C    d2 [6] $end
$var wire      1 D    d2 [5] $end
$var wire      1 E    d2 [4] $end
$var wire      1 F    d2 [3] $end
$var wire      1 G    d2 [2] $end
$var wire      1 H    d2 [1] $end
$var wire      1 I    d2 [0] $end
$var wire      8 /!   d3 [7:0] $end
$var wire      2 S    s [1:0] $end
$var reg       8 G!   y [7:0] $end
$upscope $end


$scope module pcmux $end
$var parameter 32 H!   WIDTH  $end
$var wire      8 -!   d0 [7:0] $end
$var wire      8 .!   d1 [7:0] $end
$var wire      8 /!   d2 [7:0] $end
$var wire      8 I!   d3 [7:0] $end
$var wire      2 R    s [1:0] $end
$var reg       8 J!   y [7:0] $end
$upscope $end


$scope module wdmux $end
$var parameter 32 K!   WIDTH  $end
$var wire      8 .!   d0 [7:0] $end
$var wire      8 &!   d1 [7:0] $end
$var wire      1 L    s  $end
$var wire      8 )!   y [7:0] $end
$upscope $end


$scope module rf $end
$var parameter 32 L!   WIDTH  $end
$var parameter 32 M!   REGBITS  $end
$var wire      1 #    clk  $end
$var wire      1 O    regwrite  $end
$var wire      3 !!   ra1 [2:0] $end
$var wire      3 "!   ra2 [2:0] $end
$var wire      3 #!   wa [2:0] $end
$var wire      8 )!   wd [7:0] $end
$var wire      8 '!   rd1 [7:0] $end
$var wire      8 (!   rd2 [7:0] $end
$upscope $end


$scope module alunit $end
$var parameter 32 N!   WIDTH  $end
$var wire      8 +!   a [7:0] $end
$var wire      8 ,!   b [7:0] $end
$var wire      3 X    alucont [2:0] $end
$var reg       8 O!   result [7:0] $end
$var wire      8 P!   b2 [7:0] $end
$var wire      8 Q!   sum [7:0] $end
$var wire      8 R!   slt [7:0] $end
$upscope $end


$scope module zd $end
$var parameter 32 S!   WIDTH  $end
$var wire      8 -!   a [7:0] $end
$var wire      1 J    y  $end
$upscope $end

$upscope $end

$upscope $end

$upscope $end

$enddefinitions $end
#220
$dumpvars
b1000 S!
b1000 N!
b11 M!
b1000 L!
b1000 K!
b1000 H!
b1000 E!
b1000 D!
b1000 C!
b1000 A!
b1000 ?!
b1000 =!
b1000 ;!
b1000 9!
b1000 7!
b1000 5!
b1000 3!
b1000 1!
b11 0!
b1 ~
b0 }
b11 |
b1000 {
b10 u
b100 t
b0 s
b101000 r
b100000 q
b1101 p
b1100 o
b1011 n
b1010 m
b1001 l
b1000 k
b111 j
b110 i
b101 h
b100 g
b11 f
b10 e
b1 d
b11 "
b1000 !
0#
0$
b10000000 %
1&
0'
b0 (
bx )
1*
0+
0,
0-
0.
0/
00
01
x2
x3
x4
x5
x6
x7
x8
x9
x:
x;
x<
x=
x>
x?
x@
xA
xB
xC
xD
xE
xF
xG
xH
xI
0J
0K
0L
0M
1N
0O
0P
b0 Q
b0 R
b1 S
1T
0U
0V
0W
b10 X
1Y
0Z
0[
0\
0]
0^
0_
b0 `
b1 a
b0 b
b1000 c
b1 v
b10 w
1x
0y
b10 z
bx !!
bx "!
bx #!
b0 $!
b1 %!
b10000000 &!
bx '!
bx (!
b1 )!
bx *!
b0 +!
b1 ,!
b1 -!
b1 .!
bx00 /!
bx 2!
bx 4!
bx 6!
b10000000 8!
b0 :!
b10000000 <!
bx >!
bx @!
b1 B!
b1 F!
b1 G!
b0 I!
b1 J!
b1 O!
b1 P!
b1 Q!
b0 R!
$end
#225
1#
b1 :!
b10 v
b1 $!
b1 (
b1 +!
b10 Q!
b11 w
b100 c
b10 O!
b10 -!
b10 %
0T
1U
b10 J!
b10 %!
#250
0#
#275
1#
b10 B!
b10 <!
b10 :!
b10 6!
b11 v
02
03
04
05
06
07
18
09
b10 $!
b10 &!
b10 .!
b10 )!
b10 (
b10 +!
b10 "!
b10 #!
b0 !!
b0 '!
b11 Q!
b100 w
b10 c
b11 O!
b11 -!
b0 %
0U
1V
b11 J!
b11 %!
#300
0#
#325
1#
b11 B!
b0 >!
b0 <!
b11 :!
b0 4!
b100 v
0:
0;
0<
0=
0>
0?
0@
0A
b11 $!
b0 &!
b0 *!
b11 .!
b11 )!
b11 (
b11 +!
b100 Q!
b101 w
b1 c
b100 O!
b100 -!
b1000100 %
0V
1W
b100 J!
b100 %!
#350
0#
#375
1#
b100 B!
b1000100 <!
b100 :!
b1000100 2!
b101 v
0B
1C
0D
0E
0F
1G
0H
0I
b100 $!
b1000100 &!
b100 .!
b100 )!
b100 (
b100 +!
b10000 /!
b101 Q!
b110 w
b0 c
0x
0Y
b11 a
b101 O!
0N
b101 -!
b10000000 %
b11 S
0&
0W
b101 J!
b10000 G!
b10000 ,!
b101 %!
b10000 P!
b10100 Q!
b10100 O!
b10100 -!
b10100 J!
b10100 %!
#400
0#
#425
1#
b10100 B!
b10000000 <!
b110 v
b10000000 &!
b10100 .!
b10100 )!
b111 w
b10 a
1[
1K
b10 S
b0 +!
b10000 Q!
b1000100 G!
b10000 O!
b10000 -!
b1000100 ,!
b1000100 P!
b1000100 Q!
b10000 J!
b1000100 O!
b1000100 -!
b10000 %!
b1000100 J!
b1000100 %!
#450
0#
#475
1#
b1000100 B!
b111 v
b1000100 .!
b1000100 )!
b1000 w
0[
b0 a
1Y
1]
1M
1&
b0 S
0K
b100 +!
b1000100 (
b1001000 Q!
bx G!
b1001000 O!
b1001000 -!
b101 %
bx ,!
bx P!
bx Q!
b0x R!
b1001000 J!
bx O!
bx -!
b1001000 %!
xJ
bx J!
bx %!
#500
0#
#525
1#
bx B!
b101 <!
b1000 v
b101 &!
bx .!
bx (
bx )!
b1 w
0Y
0]
1^
1\
1L
1O
0M
0&
b100 (
b101 )!
b10000000 %
#550
0#
#575
1#
b10000000 <!
b1 v
b101 (!
b10000000 &!
b10000000 )!
b10 w
0^
0\
1Y
b1000 c
b1 a
1x
1N
b1 S
1T
1&
0L
0O
bx )!
b1 G!
b1 ,!
b1 P!
b101 Q!
b0 R!
b101 O!
b101 -!
0J
b101 J!
b101 %!
#600
0#
#625
1#
b101 B!
b101 @!
b101 :!
b10 v
b101 $!
b101 )
b101 .!
b101 )!
b101 (
b101 +!
b110 Q!
b11 w
b100 c
b110 O!
b110 -!
b111 %
0T
1U
b110 J!
b110 %!
#650
0#
#675
1#
b110 B!
b111 <!
b110 :!
b111 6!
b11 v
17
19
b110 $!
b111 &!
b110 .!
b110 )!
b110 (
b110 +!
b111 "!
b111 #!
bx (!
b111 Q!
b100 w
b10 c
b111 O!
b111 -!
b0 %
0U
1V
b111 J!
b111 %!
#700
0#
#725
1#
b111 B!
bx @!
b0 <!
b111 :!
b100 v
b111 $!
b0 &!
bx )
b111 .!
b111 )!
b111 (
b111 +!
b1000 Q!
b101 w
b1 c
b1000 O!
b1000 -!
b1000000 %
0V
1W
b1000 J!
b1000 %!
#750
0#
#775
1#
b1000 B!
b1000000 <!
b1000 :!
b1000000 2!
b101 v
0G
b1000 $!
b1000000 &!
b1000 .!
b1000 )!
b1000 (
b1000 +!
b0 /!
b1001 Q!
b110 w
b0 c
0x
0Y
b11 a
b1001 O!
0N
b1001 -!
b10000000 %
b11 S
0&
0W
b1001 J!
b0 G!
b0 ,!
b1001 %!
b0 P!
b1000 Q!
b1000 O!
b1000 -!
b1000 J!
b1000 %!
#800
0#
#825
1#
b10000000 <!
b110 v
b10000000 &!
b111 w
b10 a
1[
1K
b10 S
b0 +!
b0 Q!
b1000000 G!
b0 O!
b0 -!
b1000000 ,!
b1000000 P!
1J
b1000000 Q!
b0 J!
b1000000 O!
b1000000 -!
b0 %!
0J
b1000000 J!
b1000000 %!
#850
0#
